{
"meta":{"test_sets":[],"test_metrics":[],"learn_metrics":[{"best_value":"Min","name":"Logloss"}],"launch_mode":"Train","parameters":"","iteration_count":1000,"learn_sets":["learn"],"name":"experiment"},
"iterations":[
{"learn":[0.6639393452],"iteration":0,"passed_time":0.155395001,"remaining_time":155.239606},
{"learn":[0.6388213068],"iteration":1,"passed_time":0.1613640104,"remaining_time":80.52064118},
{"learn":[0.6132716052],"iteration":2,"passed_time":0.1662195743,"remaining_time":55.2403052},
{"learn":[0.5916785808],"iteration":3,"passed_time":0.1708515637,"remaining_time":42.54203936},
{"learn":[0.5713598114],"iteration":4,"passed_time":0.1768347351,"remaining_time":35.19011229},
{"learn":[0.5521126377],"iteration":5,"passed_time":0.1816003707,"remaining_time":30.08512808},
{"learn":[0.5338417531],"iteration":6,"passed_time":0.1859468394,"remaining_time":26.37788737},
{"learn":[0.5173162273],"iteration":7,"passed_time":0.190217882,"remaining_time":23.58701737},
{"learn":[0.5026571907],"iteration":8,"passed_time":0.1961554317,"remaining_time":21.59889253},
{"learn":[0.4886833352],"iteration":9,"passed_time":0.2005783494,"remaining_time":19.85725659},
{"learn":[0.4762175652],"iteration":10,"passed_time":0.204971356,"remaining_time":18.42878828},
{"learn":[0.4644440621],"iteration":11,"passed_time":0.2100573129,"remaining_time":17.29471876},
{"learn":[0.454535478],"iteration":12,"passed_time":0.2144183065,"remaining_time":16.27929758},
{"learn":[0.4448383469],"iteration":13,"passed_time":0.218822334,"remaining_time":15.41134438},
{"learn":[0.4372079111],"iteration":14,"passed_time":0.2233005936,"remaining_time":14.66340564},
{"learn":[0.4303554854],"iteration":15,"passed_time":0.228659771,"remaining_time":14.06257591},
{"learn":[0.4226493168],"iteration":16,"passed_time":0.2333165319,"remaining_time":13.49118535},
{"learn":[0.4152635166],"iteration":17,"passed_time":0.2378827416,"remaining_time":12.97782512},
{"learn":[0.4084675243],"iteration":18,"passed_time":0.2439219019,"remaining_time":12.59407293},
{"learn":[0.40219002],"iteration":19,"passed_time":0.2488015229,"remaining_time":12.19127462},
{"learn":[0.396537269],"iteration":20,"passed_time":0.2533381267,"remaining_time":11.81038219},
{"learn":[0.3912345655],"iteration":21,"passed_time":0.2586064635,"remaining_time":11.49623279},
{"learn":[0.3861205766],"iteration":22,"passed_time":0.263066699,"remaining_time":11.17461587},
{"learn":[0.382161097],"iteration":23,"passed_time":0.2673307324,"remaining_time":10.87144978},
{"learn":[0.3776558026],"iteration":24,"passed_time":0.2715703547,"remaining_time":10.59124383},
{"learn":[0.3735521833],"iteration":25,"passed_time":0.2775037285,"remaining_time":10.3957166},
{"learn":[0.3697142274],"iteration":26,"passed_time":0.2818744708,"remaining_time":10.15792075},
{"learn":[0.3659681073],"iteration":27,"passed_time":0.2862107828,"remaining_time":9.93560289},
{"learn":[0.3625398373],"iteration":28,"passed_time":0.2916713008,"remaining_time":9.765959761},
{"learn":[0.3590703896],"iteration":29,"passed_time":0.2962430144,"remaining_time":9.578524133},
{"learn":[0.3561098711],"iteration":30,"passed_time":0.3006402703,"remaining_time":9.397432965},
{"learn":[0.3539819953],"iteration":31,"passed_time":0.3055878356,"remaining_time":9.244032027},
{"learn":[0.3508339923],"iteration":32,"passed_time":0.3101528212,"remaining_time":9.088417519},
{"learn":[0.3481219826],"iteration":33,"passed_time":0.314416709,"remaining_time":8.933133557},
{"learn":[0.3455353655],"iteration":34,"passed_time":0.3187207966,"remaining_time":8.787587678},
{"learn":[0.3433776439],"iteration":35,"passed_time":0.3239105463,"remaining_time":8.67360463},
{"learn":[0.3411287172],"iteration":36,"passed_time":0.3282532373,"remaining_time":8.54345588},
{"learn":[0.3392777442],"iteration":37,"passed_time":0.3326639078,"remaining_time":8.421649455},
{"learn":[0.3375166861],"iteration":38,"passed_time":0.3382750249,"remaining_time":8.335443561},
{"learn":[0.3352096986],"iteration":39,"passed_time":0.3426875771,"remaining_time":8.224501851},
{"learn":[0.3338798295],"iteration":40,"passed_time":0.3469736782,"remaining_time":8.11579896},
{"learn":[0.3320183207],"iteration":41,"passed_time":0.3514953571,"remaining_time":8.017441717},
{"learn":[0.330769141],"iteration":42,"passed_time":0.3565911294,"remaining_time":7.936225834},
{"learn":[0.3290102945],"iteration":43,"passed_time":0.360967991,"remaining_time":7.842849986},
{"learn":[0.3279829913],"iteration":44,"passed_time":0.3652504503,"remaining_time":7.751426223},
{"learn":[0.3268005647],"iteration":45,"passed_time":0.3695983112,"remaining_time":7.665147585},
{"learn":[0.3257056544],"iteration":46,"passed_time":0.3746306576,"remaining_time":7.596234398},
{"learn":[0.3243963462],"iteration":47,"passed_time":0.3787975994,"remaining_time":7.512819054},
{"learn":[0.3231560021],"iteration":48,"passed_time":0.3830880594,"remaining_time":7.435035601},
{"learn":[0.3220997892],"iteration":49,"passed_time":0.3877631156,"remaining_time":7.367499197},
{"learn":[0.3211130858],"iteration":50,"passed_time":0.3924592531,"remaining_time":7.302820219},
{"learn":[0.319578805],"iteration":51,"passed_time":0.3969817664,"remaining_time":7.237282972},
{"learn":[0.3184335135],"iteration":52,"passed_time":0.4026737562,"remaining_time":7.194944284},
{"learn":[0.3173569114],"iteration":53,"passed_time":0.4073884544,"remaining_time":7.136842183},
{"learn":[0.3161119379],"iteration":54,"passed_time":0.4115830395,"remaining_time":7.071744952},
{"learn":[0.3153326278],"iteration":55,"passed_time":0.4160606693,"remaining_time":7.013594139},
{"learn":[0.3144104645],"iteration":56,"passed_time":0.4213255195,"remaining_time":6.970350261},
{"learn":[0.3132536279],"iteration":57,"passed_time":0.42556521,"remaining_time":6.911765997},
{"learn":[0.3127208909],"iteration":58,"passed_time":0.4298763654,"remaining_time":6.856163726},
{"learn":[0.3119536127],"iteration":59,"passed_time":0.4346275991,"remaining_time":6.809165719},
{"learn":[0.3111082376],"iteration":60,"passed_time":0.4393316035,"remaining_time":6.762825831},
{"learn":[0.3103994134],"iteration":61,"passed_time":0.4436197262,"remaining_time":6.711537147},
{"learn":[0.3098412138],"iteration":62,"passed_time":0.4478429384,"remaining_time":6.660775131},
{"learn":[0.3091523956],"iteration":63,"passed_time":0.452941289,"remaining_time":6.624266351},
{"learn":[0.308423855],"iteration":64,"passed_time":0.4572339874,"remaining_time":6.577135049},
{"learn":[0.3077504151],"iteration":65,"passed_time":0.4616486409,"remaining_time":6.533027737},
{"learn":[0.3071833517],"iteration":66,"passed_time":0.4662853505,"remaining_time":6.493197492},
{"learn":[0.3064495889],"iteration":67,"passed_time":0.4716246163,"remaining_time":6.464031505},
{"learn":[0.305555214],"iteration":68,"passed_time":0.475903022,"remaining_time":6.421242225},
{"learn":[0.3046419819],"iteration":69,"passed_time":0.4803546064,"remaining_time":6.381854056},
{"learn":[0.3037851342],"iteration":70,"passed_time":0.4859421482,"remaining_time":6.358313461},
{"learn":[0.3032770816],"iteration":71,"passed_time":0.4902186278,"remaining_time":6.318373425},
{"learn":[0.3023473588],"iteration":72,"passed_time":0.4944572774,"remaining_time":6.278930084},
{"learn":[0.3017864502],"iteration":73,"passed_time":0.4986961384,"remaining_time":6.240440867},
{"learn":[0.3012777186],"iteration":74,"passed_time":0.5042693271,"remaining_time":6.219321701},
{"learn":[0.3007547735],"iteration":75,"passed_time":0.5087693314,"remaining_time":6.185563976},
{"learn":[0.3001498485],"iteration":76,"passed_time":0.5131063299,"remaining_time":6.15061224},
{"learn":[0.2994078892],"iteration":77,"passed_time":0.5186191444,"remaining_time":6.130344245},
{"learn":[0.2987376646],"iteration":78,"passed_time":0.5227680625,"remaining_time":6.094549184},
{"learn":[0.2982725754],"iteration":79,"passed_time":0.5273955516,"remaining_time":6.065048843},
{"learn":[0.2978628907],"iteration":80,"passed_time":0.5316891848,"remaining_time":6.032374825},
{"learn":[0.2973715207],"iteration":81,"passed_time":0.5370236273,"remaining_time":6.012044999},
{"learn":[0.2965599685],"iteration":82,"passed_time":0.5414157799,"remaining_time":5.981665906},
{"learn":[0.2961178478],"iteration":83,"passed_time":0.5468348867,"remaining_time":5.963104241},
{"learn":[0.295662316],"iteration":84,"passed_time":0.5522446114,"remaining_time":5.944750817},
{"learn":[0.2950774997],"iteration":85,"passed_time":0.5569258919,"remaining_time":5.918956572},
{"learn":[0.2946021713],"iteration":86,"passed_time":0.5615862088,"remaining_time":5.893427686},
{"learn":[0.2942396278],"iteration":87,"passed_time":0.5671042534,"remaining_time":5.877262262},
{"learn":[0.2938081976],"iteration":88,"passed_time":0.571855956,"remaining_time":5.853491864},
{"learn":[0.2931077069],"iteration":89,"passed_time":0.5763985977,"remaining_time":5.828030266},
{"learn":[0.2926025223],"iteration":90,"passed_time":0.5805868264,"remaining_time":5.799488189},
{"learn":[0.2920822321],"iteration":91,"passed_time":0.5859928665,"remaining_time":5.783494813},
{"learn":[0.2915519553],"iteration":92,"passed_time":0.5904529051,"remaining_time":5.758503064},
{"learn":[0.2909317606],"iteration":93,"passed_time":0.59475903,"remaining_time":5.732464693},
{"learn":[0.2903802461],"iteration":94,"passed_time":0.6001433694,"remaining_time":5.717155256},
{"learn":[0.2900542153],"iteration":95,"passed_time":0.6046046959,"remaining_time":5.693360887},
{"learn":[0.2895846478],"iteration":96,"passed_time":0.6087669451,"remaining_time":5.667180943},
{"learn":[0.2888941048],"iteration":97,"passed_time":0.613044895,"remaining_time":5.642515258},
{"learn":[0.2885536147],"iteration":98,"passed_time":0.6186792647,"remaining_time":5.630606237},
{"learn":[0.2881633301],"iteration":99,"passed_time":0.6228554981,"remaining_time":5.605699483},
{"learn":[0.287691186],"iteration":100,"passed_time":0.6272545852,"remaining_time":5.583186853},
{"learn":[0.2874449601],"iteration":101,"passed_time":0.6320796426,"remaining_time":5.564779598},
{"learn":[0.2869046915],"iteration":102,"passed_time":0.6366273657,"remaining_time":5.544220845},
{"learn":[0.2865767806],"iteration":103,"passed_time":0.6407871443,"remaining_time":5.520627705},
{"learn":[0.2861188422],"iteration":104,"passed_time":0.6450809219,"remaining_time":5.498546906},
{"learn":[0.2855144414],"iteration":105,"passed_time":0.6508668764,"remaining_time":5.489386675},
{"learn":[0.2849224354],"iteration":106,"passed_time":0.6551480397,"remaining_time":5.467730836},
{"learn":[0.2846164177],"iteration":107,"passed_time":0.6592065938,"remaining_time":5.444558164},
{"learn":[0.2843753309],"iteration":108,"passed_time":0.6645390788,"remaining_time":5.432149717},
{"learn":[0.2839372984],"iteration":109,"passed_time":0.6689996844,"remaining_time":5.412815628},
{"learn":[0.2835680254],"iteration":110,"passed_time":0.6733834532,"remaining_time":5.393134143},
{"learn":[0.2830727735],"iteration":111,"passed_time":0.6777908168,"remaining_time":5.373912904},
{"learn":[0.2827473099],"iteration":112,"passed_time":0.683881302,"remaining_time":5.368165619},
{"learn":[0.2824598641],"iteration":113,"passed_time":0.6881494721,"remaining_time":5.348249406},
{"learn":[0.2819745539],"iteration":114,"passed_time":0.6925372371,"remaining_time":5.329525694},
{"learn":[0.281531913],"iteration":115,"passed_time":0.6978956732,"remaining_time":5.318446337},
{"learn":[0.2812924303],"iteration":116,"passed_time":0.7020449889,"remaining_time":5.298339532},
{"learn":[0.2810350921],"iteration":117,"passed_time":0.7060271561,"remaining_time":5.277253828},
{"learn":[0.2806796228],"iteration":118,"passed_time":0.7100007598,"remaining_time":5.25639218},
{"learn":[0.2803628504],"iteration":119,"passed_time":0.7150883721,"remaining_time":5.243981395},
{"learn":[0.2799763257],"iteration":120,"passed_time":0.7192959734,"remaining_time":5.225298848},
{"learn":[0.2795955526],"iteration":121,"passed_time":0.7234657045,"remaining_time":5.206581054},
{"learn":[0.2792157507],"iteration":122,"passed_time":0.7275759215,"remaining_time":5.187675473},
{"learn":[0.2787781362],"iteration":123,"passed_time":0.7327667627,"remaining_time":5.176642614},
{"learn":[0.2785253526],"iteration":124,"passed_time":0.7374618122,"remaining_time":5.162232685},
{"learn":[0.2781104559],"iteration":125,"passed_time":0.7418923586,"remaining_time":5.146142233},
{"learn":[0.2777548674],"iteration":126,"passed_time":0.7467464354,"remaining_time":5.133146756},
{"learn":[0.2773996912],"iteration":127,"passed_time":0.7509743658,"remaining_time":5.116012867},
{"learn":[0.2771626351],"iteration":128,"passed_time":0.7551888817,"remaining_time":5.098988496},
{"learn":[0.2765292361],"iteration":129,"passed_time":0.7592369366,"remaining_time":5.081047191},
{"learn":[0.2762513385],"iteration":130,"passed_time":0.7646617711,"remaining_time":5.072450985},
{"learn":[0.2759565367],"iteration":131,"passed_time":0.7688421302,"remaining_time":5.055719462},
{"learn":[0.2755808621],"iteration":132,"passed_time":0.7733582637,"remaining_time":5.041365524},
{"learn":[0.2752834661],"iteration":133,"passed_time":0.7783013318,"remaining_time":5.029917562},
{"learn":[0.2749568189],"iteration":134,"passed_time":0.7827485385,"remaining_time":5.015388784},
{"learn":[0.2747124558],"iteration":135,"passed_time":0.7870978429,"remaining_time":5.000386296},
{"learn":[0.2743174544],"iteration":136,"passed_time":0.7915725753,"remaining_time":4.986329434},
{"learn":[0.2738938356],"iteration":137,"passed_time":0.796909785,"remaining_time":4.977798802},
{"learn":[0.2735783078],"iteration":138,"passed_time":0.8015137621,"remaining_time":4.964772296},
{"learn":[0.2733178761],"iteration":139,"passed_time":0.8060464161,"remaining_time":4.951427985},
{"learn":[0.2729960918],"iteration":140,"passed_time":0.8110462902,"remaining_time":4.941055059},
{"learn":[0.2726464011],"iteration":141,"passed_time":0.8154707059,"remaining_time":4.927280744},
{"learn":[0.2717729542],"iteration":142,"passed_time":0.8196760553,"remaining_time":4.912324332},
{"learn":[0.2715081041],"iteration":143,"passed_time":0.8237486263,"remaining_time":4.896727945},
{"learn":[0.2713078051],"iteration":144,"passed_time":0.8289670453,"remaining_time":4.88804706},
{"learn":[0.2710944613],"iteration":145,"passed_time":0.8331591375,"remaining_time":4.873410298},
{"learn":[0.2707107867],"iteration":146,"passed_time":0.8379609105,"remaining_time":4.862453447},
{"learn":[0.2704960171],"iteration":147,"passed_time":0.8420964469,"remaining_time":4.847744411},
{"learn":[0.270259015],"iteration":148,"passed_time":0.8471544407,"remaining_time":4.838445832},
{"learn":[0.2699183268],"iteration":149,"passed_time":0.8514935447,"remaining_time":4.825130087},
{"learn":[0.269602684],"iteration":150,"passed_time":0.855560494,"remaining_time":4.810403043},
{"learn":[0.2694067124],"iteration":151,"passed_time":0.860655676,"remaining_time":4.801552719},
{"learn":[0.2691674705],"iteration":152,"passed_time":0.864951807,"remaining_time":4.788327977},
{"learn":[0.2686753605],"iteration":153,"passed_time":0.869232152,"remaining_time":4.775132471},
{"learn":[0.2684099116],"iteration":154,"passed_time":0.8736595053,"remaining_time":4.762853432},
{"learn":[0.2680987491],"iteration":155,"passed_time":0.8789099897,"remaining_time":4.755128406},
{"learn":[0.2677795918],"iteration":156,"passed_time":0.8832116534,"remaining_time":4.742340279},
{"learn":[0.2675050234],"iteration":157,"passed_time":0.8873209786,"remaining_time":4.728634582},
{"learn":[0.2673669587],"iteration":158,"passed_time":0.8917506121,"remaining_time":4.716743804},
{"learn":[0.2671853714],"iteration":159,"passed_time":0.8973114094,"remaining_time":4.710884899},
{"learn":[0.266917066],"iteration":160,"passed_time":0.9015604655,"remaining_time":4.698193979},
{"learn":[0.2665060171],"iteration":161,"passed_time":0.9059889026,"remaining_time":4.686535188},
{"learn":[0.266150286],"iteration":162,"passed_time":0.9114422148,"remaining_time":4.680227815},
{"learn":[0.2658401366],"iteration":163,"passed_time":0.9155509412,"remaining_time":4.667076749},
{"learn":[0.2655244457],"iteration":164,"passed_time":0.9197030306,"remaining_time":4.654254731},
{"learn":[0.2652643888],"iteration":165,"passed_time":0.9239468957,"remaining_time":4.641998259},
{"learn":[0.2650444223],"iteration":166,"passed_time":0.9290660796,"remaining_time":4.634203858},
{"learn":[0.2648424498],"iteration":167,"passed_time":0.9341365843,"remaining_time":4.626200227},
{"learn":[0.264471711],"iteration":168,"passed_time":0.9388313433,"remaining_time":4.616383706},
{"learn":[0.2641292219],"iteration":169,"passed_time":0.943030685,"remaining_time":4.604208639},
{"learn":[0.263856631],"iteration":170,"passed_time":0.9476100993,"remaining_time":4.593969429},
{"learn":[0.2636024965],"iteration":171,"passed_time":0.9527523776,"remaining_time":4.586505632},
{"learn":[0.2631923009],"iteration":172,"passed_time":0.9573467712,"remaining_time":4.576449594},
{"learn":[0.2629146273],"iteration":173,"passed_time":0.9618078859,"remaining_time":4.565823642},
{"learn":[0.2627432545],"iteration":174,"passed_time":0.9666446354,"remaining_time":4.557038996},
{"learn":[0.2624738272],"iteration":175,"passed_time":0.9708706205,"remaining_time":4.545439723},
{"learn":[0.2622382943],"iteration":176,"passed_time":0.9749381541,"remaining_time":4.53318701},
{"learn":[0.2617885808],"iteration":177,"passed_time":0.9791610617,"remaining_time":4.521743779},
{"learn":[0.2615416378],"iteration":178,"passed_time":0.984368785,"remaining_time":4.51489817},
{"learn":[0.2613669915],"iteration":179,"passed_time":0.9885213712,"remaining_time":4.503264024},
{"learn":[0.2609794557],"iteration":180,"passed_time":0.9927968191,"remaining_time":4.49226848},
{"learn":[0.2606503132],"iteration":181,"passed_time":0.9976451624,"remaining_time":4.483921664},
{"learn":[0.260299441],"iteration":182,"passed_time":1.002300228,"remaining_time":4.474750199},
{"learn":[0.2600737113],"iteration":183,"passed_time":1.006466094,"remaining_time":4.463458329},
{"learn":[0.2597483334],"iteration":184,"passed_time":1.010600128,"remaining_time":4.452103265},
{"learn":[0.259597498],"iteration":185,"passed_time":1.015907129,"remaining_time":4.445959155},
{"learn":[0.2592668108],"iteration":186,"passed_time":1.021351684,"remaining_time":4.440422028},
{"learn":[0.2590139408],"iteration":187,"passed_time":1.026326394,"remaining_time":4.432856554},
{"learn":[0.2587203516],"iteration":188,"passed_time":1.031710272,"remaining_time":4.427074235},
{"learn":[0.2585065577],"iteration":189,"passed_time":1.036632109,"remaining_time":4.41932636},
{"learn":[0.2581882694],"iteration":190,"passed_time":1.041233723,"remaining_time":4.410251736},
{"learn":[0.2576799429],"iteration":191,"passed_time":1.046802682,"remaining_time":4.40529462},
{"learn":[0.2573821218],"iteration":192,"passed_time":1.051667724,"remaining_time":4.39738784},
{"learn":[0.2572486207],"iteration":193,"passed_time":1.056848614,"remaining_time":4.390824654},
{"learn":[0.2569576244],"iteration":194,"passed_time":1.062473323,"remaining_time":4.386107819},
{"learn":[0.2568080985],"iteration":195,"passed_time":1.068397335,"remaining_time":4.382609478},
{"learn":[0.2563621269],"iteration":196,"passed_time":1.073131216,"remaining_time":4.374235364},
{"learn":[0.2561258176],"iteration":197,"passed_time":1.078140449,"remaining_time":4.367013332},
{"learn":[0.2559336159],"iteration":198,"passed_time":1.08327496,"remaining_time":4.360317804},
{"learn":[0.2557721287],"iteration":199,"passed_time":1.088402641,"remaining_time":4.353610566},
{"learn":[0.2555145399],"iteration":200,"passed_time":1.093283749,"remaining_time":4.345938884},
{"learn":[0.2551920152],"iteration":201,"passed_time":1.099123278,"remaining_time":4.34208107},
{"learn":[0.2547512935],"iteration":202,"passed_time":1.103894613,"remaining_time":4.334009883},
{"learn":[0.2543243548],"iteration":203,"passed_time":1.108829887,"remaining_time":4.326610735},
{"learn":[0.2540652389],"iteration":204,"passed_time":1.113853816,"remaining_time":4.319579432},
{"learn":[0.2538791362],"iteration":205,"passed_time":1.118097032,"remaining_time":4.309558464},
{"learn":[0.2535374744],"iteration":206,"passed_time":1.12218963,"remaining_time":4.299016313},
{"learn":[0.2532311227],"iteration":207,"passed_time":1.126739791,"remaining_time":4.290278435},
{"learn":[0.2530873134],"iteration":208,"passed_time":1.131674974,"remaining_time":4.28303782},
{"learn":[0.2528616619],"iteration":209,"passed_time":1.135771525,"remaining_time":4.272664309},
{"learn":[0.2526281456],"iteration":210,"passed_time":1.139984823,"remaining_time":4.262786851},
{"learn":[0.252436442],"iteration":211,"passed_time":1.145514305,"remaining_time":4.257855059},
{"learn":[0.2522467721],"iteration":212,"passed_time":1.150348165,"remaining_time":4.250347444},
{"learn":[0.2521015577],"iteration":213,"passed_time":1.155150646,"remaining_time":4.242749569},
{"learn":[0.2520060882],"iteration":214,"passed_time":1.160715835,"remaining_time":4.237962468},
{"learn":[0.2517719892],"iteration":215,"passed_time":1.165799962,"remaining_time":4.231422086},
{"learn":[0.2516365413],"iteration":216,"passed_time":1.169984513,"remaining_time":4.221649189},
{"learn":[0.251495854],"iteration":217,"passed_time":1.174131426,"remaining_time":4.211792548},
{"learn":[0.2511920975],"iteration":218,"passed_time":1.17924193,"remaining_time":4.205424418},
{"learn":[0.2508432609],"iteration":219,"passed_time":1.183635343,"remaining_time":4.196525307},
{"learn":[0.2506113883],"iteration":220,"passed_time":1.188141765,"remaining_time":4.188065316},
{"learn":[0.2504541656],"iteration":221,"passed_time":1.193307317,"remaining_time":4.181950866},
{"learn":[0.2503157892],"iteration":222,"passed_time":1.198236045,"remaining_time":4.175019763},
{"learn":[0.2502114866],"iteration":223,"passed_time":1.202479922,"remaining_time":4.165734015},
{"learn":[0.2500131933],"iteration":224,"passed_time":1.206599613,"remaining_time":4.156065335},
{"learn":[0.2497695141],"iteration":225,"passed_time":1.211774286,"remaining_time":4.150058838},
{"learn":[0.2496505636],"iteration":226,"passed_time":1.215953224,"remaining_time":4.140668908},
{"learn":[0.2494920128],"iteration":227,"passed_time":1.220120771,"remaining_time":4.131286121},
{"learn":[0.2493323704],"iteration":228,"passed_time":1.224516706,"remaining_time":4.122717817},
{"learn":[0.249224594],"iteration":229,"passed_time":1.229537929,"remaining_time":4.116279154},
{"learn":[0.2488660738],"iteration":230,"passed_time":1.233790841,"remaining_time":4.10729505},
{"learn":[0.2486203726],"iteration":231,"passed_time":1.237894912,"remaining_time":4.09785902},
{"learn":[0.2484541376],"iteration":232,"passed_time":1.24287447,"remaining_time":4.091350724},
{"learn":[0.2481394282],"iteration":233,"passed_time":1.247115198,"remaining_time":4.082436931},
{"learn":[0.2479845205],"iteration":234,"passed_time":1.251150211,"remaining_time":4.072893241},
{"learn":[0.2478120812],"iteration":235,"passed_time":1.255577361,"remaining_time":4.064665694},
{"learn":[0.2475938626],"iteration":236,"passed_time":1.260560871,"remaining_time":4.058261371},
{"learn":[0.2473947432],"iteration":237,"passed_time":1.264566654,"remaining_time":4.048738614},
{"learn":[0.2472147348],"iteration":238,"passed_time":1.268766907,"remaining_time":4.039881241},
{"learn":[0.24702268],"iteration":239,"passed_time":1.273518921,"remaining_time":4.032809916},
{"learn":[0.2468346036],"iteration":240,"passed_time":1.278705956,"remaining_time":4.027127886},
{"learn":[0.2466605678],"iteration":241,"passed_time":1.283001731,"remaining_time":4.018658314},
{"learn":[0.2465617245],"iteration":242,"passed_time":1.287125417,"remaining_time":4.009686997},
{"learn":[0.2463701952],"iteration":243,"passed_time":1.291837184,"remaining_time":4.002577504},
{"learn":[0.2460909708],"iteration":244,"passed_time":1.296974664,"remaining_time":3.996799475},
{"learn":[0.2458314571],"iteration":245,"passed_time":1.301450673,"remaining_time":3.988999218},
{"learn":[0.2456358121],"iteration":246,"passed_time":1.305946247,"remaining_time":3.981285521},
{"learn":[0.2454594526],"iteration":247,"passed_time":1.311371416,"remaining_time":3.976416553},
{"learn":[0.2453236143],"iteration":248,"passed_time":1.315581618,"remaining_time":3.967878696},
{"learn":[0.2450831602],"iteration":249,"passed_time":1.320128879,"remaining_time":3.960386637},
{"learn":[0.2449054225],"iteration":250,"passed_time":1.324847037,"remaining_time":3.953428011},
{"learn":[0.2446585232],"iteration":251,"passed_time":1.329672391,"remaining_time":3.946805352},
{"learn":[0.2444307328],"iteration":252,"passed_time":1.333939743,"remaining_time":3.938549361},
{"learn":[0.2442143716],"iteration":253,"passed_time":1.338201197,"remaining_time":3.930307452},
{"learn":[0.2437867001],"iteration":254,"passed_time":1.343437986,"remaining_time":3.924946272},
{"learn":[0.2435217478],"iteration":255,"passed_time":1.347772492,"remaining_time":3.916963806},
{"learn":[0.243302533],"iteration":256,"passed_time":1.352074929,"remaining_time":3.908917011},
{"learn":[0.2430295948],"iteration":257,"passed_time":1.356997138,"remaining_time":3.902681693},
{"learn":[0.2429143666],"iteration":258,"passed_time":1.362117243,"remaining_time":3.897022692},
{"learn":[0.2427561999],"iteration":259,"passed_time":1.366300501,"remaining_time":3.888701425},
{"learn":[0.2425479739],"iteration":260,"passed_time":1.370592356,"remaining_time":3.880719352},
{"learn":[0.2424421277],"iteration":261,"passed_time":1.375572793,"remaining_time":3.874705042},
{"learn":[0.2422173491],"iteration":262,"passed_time":1.379979114,"remaining_time":3.867089761},
{"learn":[0.2420494663],"iteration":263,"passed_time":1.385161557,"remaining_time":3.861662522},
{"learn":[0.241910122],"iteration":264,"passed_time":1.389295788,"remaining_time":3.853329826},
{"learn":[0.2416663244],"iteration":265,"passed_time":1.393489446,"remaining_time":3.845192682},
{"learn":[0.2414151435],"iteration":266,"passed_time":1.397510302,"remaining_time":3.836610681},
{"learn":[0.2412314632],"iteration":267,"passed_time":1.402670759,"remaining_time":3.831175356},
{"learn":[0.2409349077],"iteration":268,"passed_time":1.407131096,"remaining_time":3.823839521},
{"learn":[0.2406545492],"iteration":269,"passed_time":1.41136409,"remaining_time":3.815910317},
{"learn":[0.2404701478],"iteration":270,"passed_time":1.416068572,"remaining_time":3.809276711},
{"learn":[0.2403205929],"iteration":271,"passed_time":1.420760863,"remaining_time":3.802624662},
{"learn":[0.2402060017],"iteration":272,"passed_time":1.42495281,"remaining_time":3.794654553},
{"learn":[0.2400216182],"iteration":273,"passed_time":1.4291077,"remaining_time":3.786613832},
{"learn":[0.2398133125],"iteration":274,"passed_time":1.434443584,"remaining_time":3.781714904},
{"learn":[0.239534991],"iteration":275,"passed_time":1.439028958,"remaining_time":3.774844077},
{"learn":[0.239311122],"iteration":276,"passed_time":1.443416378,"remaining_time":3.767473074},
{"learn":[0.2391020448],"iteration":277,"passed_time":1.44768979,"remaining_time":3.75982744},
{"learn":[0.2388955217],"iteration":278,"passed_time":1.453124106,"remaining_time":3.755206024},
{"learn":[0.2386681639],"iteration":279,"passed_time":1.457339386,"remaining_time":3.747444135},
{"learn":[0.2384874063],"iteration":280,"passed_time":1.461619728,"remaining_time":3.739873966},
{"learn":[0.2383507161],"iteration":281,"passed_time":1.466291076,"remaining_time":3.733322669},
{"learn":[0.2380737668],"iteration":282,"passed_time":1.470450072,"remaining_time":3.725486577},
{"learn":[0.2378801296],"iteration":283,"passed_time":1.474544511,"remaining_time":3.717513627},
{"learn":[0.237664679],"iteration":284,"passed_time":1.479005631,"remaining_time":3.710487811},
{"learn":[0.2374122406],"iteration":285,"passed_time":1.484555849,"remaining_time":3.706198868},
{"learn":[0.237198509],"iteration":286,"passed_time":1.488903467,"remaining_time":3.698913491},
{"learn":[0.236975639],"iteration":287,"passed_time":1.493211561,"remaining_time":3.691550803},
{"learn":[0.2368446444],"iteration":288,"passed_time":1.497913064,"remaining_time":3.685177122},
{"learn":[0.2366762544],"iteration":289,"passed_time":1.502987969,"remaining_time":3.679729165},
{"learn":[0.2365171078],"iteration":290,"passed_time":1.507215771,"remaining_time":3.672219868},
{"learn":[0.2363455036],"iteration":291,"passed_time":1.511554825,"remaining_time":3.665002795},
{"learn":[0.2361743274],"iteration":292,"passed_time":1.516488469,"remaining_time":3.659240093},
{"learn":[0.2361001666],"iteration":293,"passed_time":1.52062608,"remaining_time":3.651571472},
{"learn":[0.2358085958],"iteration":294,"passed_time":1.524891494,"remaining_time":3.644232214},
{"learn":[0.235702635],"iteration":295,"passed_time":1.52899719,"remaining_time":3.636533856},
{"learn":[0.235470689],"iteration":296,"passed_time":1.534376842,"remaining_time":3.631875152},
{"learn":[0.2352633387],"iteration":297,"passed_time":1.538491463,"remaining_time":3.624231567},
{"learn":[0.2351519582],"iteration":298,"passed_time":1.542596541,"remaining_time":3.616589215},
{"learn":[0.2348892422],"iteration":299,"passed_time":1.548140365,"remaining_time":3.612327519},
{"learn":[0.2346616471],"iteration":300,"passed_time":1.55290797,"remaining_time":3.606254721},
{"learn":[0.2344229953],"iteration":301,"passed_time":1.557176015,"remaining_time":3.599035956},
{"learn":[0.2342333282],"iteration":302,"passed_time":1.561331178,"remaining_time":3.591577001},
{"learn":[0.2341065221],"iteration":303,"passed_time":1.566966059,"remaining_time":3.587527556},
{"learn":[0.2339921392],"iteration":304,"passed_time":1.571085417,"remaining_time":3.580014311},
{"learn":[0.2338379178],"iteration":305,"passed_time":1.575010755,"remaining_time":3.572083215},
{"learn":[0.2334715367],"iteration":306,"passed_time":1.579994109,"remaining_time":3.566566506},
{"learn":[0.233364476],"iteration":307,"passed_time":1.584227859,"remaining_time":3.559369085},
{"learn":[0.233156627],"iteration":308,"passed_time":1.58833555,"remaining_time":3.551908949},
{"learn":[0.2329903676],"iteration":309,"passed_time":1.592494605,"remaining_time":3.544584765},
{"learn":[0.2327347698],"iteration":310,"passed_time":1.597335901,"remaining_time":3.538792398},
{"learn":[0.2326094546],"iteration":311,"passed_time":1.602128593,"remaining_time":3.532898949},
{"learn":[0.2322670448],"iteration":312,"passed_time":1.606277992,"remaining_time":3.525600578},
{"learn":[0.2320540682],"iteration":313,"passed_time":1.610524574,"remaining_time":3.518534578},
{"learn":[0.2319471982],"iteration":314,"passed_time":1.615897743,"remaining_time":3.513936361},
{"learn":[0.2317629062],"iteration":315,"passed_time":1.620078155,"remaining_time":3.50675145},
{"learn":[0.2316065948],"iteration":316,"passed_time":1.624071925,"remaining_time":3.499183359},
{"learn":[0.2313831334],"iteration":317,"passed_time":1.62872054,"remaining_time":3.493042164},
{"learn":[0.2311741554],"iteration":318,"passed_time":1.633361182,"remaining_time":3.486893307},
{"learn":[0.2310673251],"iteration":319,"passed_time":1.637270505,"remaining_time":3.479199824},
{"learn":[0.23076434],"iteration":320,"passed_time":1.641270567,"remaining_time":3.471721854},
{"learn":[0.2306530375],"iteration":321,"passed_time":1.646532914,"remaining_time":3.46692334},
{"learn":[0.2304746388],"iteration":322,"passed_time":1.650983795,"remaining_time":3.460421142},
{"learn":[0.2302893014],"iteration":323,"passed_time":1.655173218,"remaining_time":3.453386097},
{"learn":[0.230190623],"iteration":324,"passed_time":1.659331963,"remaining_time":3.446304847},
{"learn":[0.2300821726],"iteration":325,"passed_time":1.664372372,"remaining_time":3.441064351},
{"learn":[0.2298801403],"iteration":326,"passed_time":1.668382279,"remaining_time":3.433704202},
{"learn":[0.2296363624],"iteration":327,"passed_time":1.6725879,"remaining_time":3.426765454},
{"learn":[0.2294924741],"iteration":328,"passed_time":1.677137344,"remaining_time":3.420544553},
{"learn":[0.2292163433],"iteration":329,"passed_time":1.681938387,"remaining_time":3.414844604},
{"learn":[0.2290813512],"iteration":330,"passed_time":1.6858391,"remaining_time":3.407330387},
{"learn":[0.2288600213],"iteration":331,"passed_time":1.69015336,"remaining_time":3.400670013},
{"learn":[0.2284968956],"iteration":332,"passed_time":1.695391156,"remaining_time":3.395873576},
{"learn":[0.2283352819],"iteration":333,"passed_time":1.699755191,"remaining_time":3.389332207},
{"learn":[0.2280344233],"iteration":334,"passed_time":1.70396965,"remaining_time":3.382506916},
{"learn":[0.2277813019],"iteration":335,"passed_time":1.708449991,"remaining_time":3.376222602},
{"learn":[0.2276117846],"iteration":336,"passed_time":1.71351064,"remaining_time":3.371090665},
{"learn":[0.2274767374],"iteration":337,"passed_time":1.717963041,"remaining_time":3.364767849},
{"learn":[0.2271923462],"iteration":338,"passed_time":1.722170694,"remaining_time":3.357978846},
{"learn":[0.2269122039],"iteration":339,"passed_time":1.727576237,"remaining_time":3.353530341},
{"learn":[0.2264697904],"iteration":340,"passed_time":1.731745019,"remaining_time":3.346686123},
{"learn":[0.2261434379],"iteration":341,"passed_time":1.735764968,"remaining_time":3.339571195},
{"learn":[0.2259299061],"iteration":342,"passed_time":1.739848675,"remaining_time":3.332596442},
{"learn":[0.2257075424],"iteration":343,"passed_time":1.744665038,"remaining_time":3.327035654},
{"learn":[0.2253464401],"iteration":344,"passed_time":1.749454186,"remaining_time":3.321427513},
{"learn":[0.2250450514],"iteration":345,"passed_time":1.753581705,"remaining_time":3.314573512},
{"learn":[0.2247984596],"iteration":346,"passed_time":1.757733053,"remaining_time":3.307780067},
{"learn":[0.2246100657],"iteration":347,"passed_time":1.76285207,"remaining_time":3.302814798},
{"learn":[0.2244860852],"iteration":348,"passed_time":1.76706008,"remaining_time":3.296149318},
{"learn":[0.2242696655],"iteration":349,"passed_time":1.770899753,"remaining_time":3.288813827},
{"learn":[0.2241070039],"iteration":350,"passed_time":1.775157687,"remaining_time":3.282271621},
{"learn":[0.2238459315],"iteration":351,"passed_time":1.779754908,"remaining_time":3.276366991},
{"learn":[0.2237059616],"iteration":352,"passed_time":1.784068026,"remaining_time":3.269949046},
{"learn":[0.2235766588],"iteration":353,"passed_time":1.788245224,"remaining_time":3.263294956},
{"learn":[0.223386392],"iteration":354,"passed_time":1.793291585,"remaining_time":3.258234007},
{"learn":[0.2232675761],"iteration":355,"passed_time":1.797578819,"remaining_time":3.251799886},
{"learn":[0.2231673639],"iteration":356,"passed_time":1.801624721,"remaining_time":3.244943125},
{"learn":[0.2230563235],"iteration":357,"passed_time":1.805769068,"remaining_time":3.238278608},
{"learn":[0.2228528125],"iteration":358,"passed_time":1.811330691,"remaining_time":3.234158699},
{"learn":[0.2226337511],"iteration":359,"passed_time":1.815733552,"remaining_time":3.22797076},
{"learn":[0.2224731211],"iteration":360,"passed_time":1.819772297,"remaining_time":3.221148194},
{"learn":[0.2223075273],"iteration":361,"passed_time":1.824002619,"remaining_time":3.21467865},
{"learn":[0.2222196452],"iteration":362,"passed_time":1.828926467,"remaining_time":3.209438457},
{"learn":[0.2219998764],"iteration":363,"passed_time":1.8331174,"remaining_time":3.202919414},
{"learn":[0.2217159265],"iteration":364,"passed_time":1.837182754,"remaining_time":3.196194654},
{"learn":[0.2213657823],"iteration":365,"passed_time":1.842197491,"remaining_time":3.191128987},
{"learn":[0.221212333],"iteration":366,"passed_time":1.846993325,"remaining_time":3.185686035},
{"learn":[0.2210548523],"iteration":367,"passed_time":1.851205692,"remaining_time":3.179244558},
{"learn":[0.2209023744],"iteration":368,"passed_time":1.855398887,"remaining_time":3.172782378},
{"learn":[0.2207364683],"iteration":369,"passed_time":1.860589346,"remaining_time":3.168030508},
{"learn":[0.2205793854],"iteration":370,"passed_time":1.864611136,"remaining_time":3.161294891},
{"learn":[0.2203371414],"iteration":371,"passed_time":1.868648363,"remaining_time":3.154599925},
{"learn":[0.2202129332],"iteration":372,"passed_time":1.873257792,"remaining_time":3.14888106},
{"learn":[0.2199192357],"iteration":373,"passed_time":1.877805077,"remaining_time":3.143064112},
{"learn":[0.2196887023],"iteration":374,"passed_time":1.881816461,"remaining_time":3.136360769},
{"learn":[0.2194668187],"iteration":375,"passed_time":1.885950016,"remaining_time":3.129874495},
{"learn":[0.2193282597],"iteration":376,"passed_time":1.890478089,"remaining_time":3.124052651},
{"learn":[0.2191294335],"iteration":377,"passed_time":1.894822298,"remaining_time":3.117935105},
{"learn":[0.2189864054],"iteration":378,"passed_time":1.899019686,"remaining_time":3.111586346},
{"learn":[0.2188048779],"iteration":379,"passed_time":1.903127444,"remaining_time":3.105102671},
{"learn":[0.2186782451],"iteration":380,"passed_time":1.90796722,"remaining_time":3.099820759},
{"learn":[0.2185739858],"iteration":381,"passed_time":1.912496727,"remaining_time":3.094039207},
{"learn":[0.2183754078],"iteration":382,"passed_time":1.916671558,"remaining_time":3.087692824},
{"learn":[0.2181729542],"iteration":383,"passed_time":1.920798016,"remaining_time":3.081280151},
{"learn":[0.2179270598],"iteration":384,"passed_time":1.926319529,"remaining_time":3.077107819},
{"learn":[0.2178149108],"iteration":385,"passed_time":1.930394532,"remaining_time":3.070627572},
{"learn":[0.217653473],"iteration":386,"passed_time":1.934735138,"remaining_time":3.064580463},
{"learn":[0.2175133266],"iteration":387,"passed_time":1.939543662,"remaining_time":3.059280209},
{"learn":[0.2173816337],"iteration":388,"passed_time":1.944189918,"remaining_time":3.053727609},
{"learn":[0.2170854716],"iteration":389,"passed_time":1.948593081,"remaining_time":3.047799434},
{"learn":[0.2169584342],"iteration":390,"passed_time":1.952720918,"remaining_time":3.041450227},
{"learn":[0.2168452958],"iteration":391,"passed_time":1.957560435,"remaining_time":3.036216184},
{"learn":[0.2166170617],"iteration":392,"passed_time":1.961875553,"remaining_time":3.0301742},
{"learn":[0.2163340558],"iteration":393,"passed_time":1.96630232,"remaining_time":3.024312706},
{"learn":[0.2162302457],"iteration":394,"passed_time":1.970444722,"remaining_time":3.018022928},
{"learn":[0.2161058412],"iteration":395,"passed_time":1.975306842,"remaining_time":3.012841749},
{"learn":[0.2159364149],"iteration":396,"passed_time":1.97927056,"remaining_time":3.006297602},
{"learn":[0.2157869898],"iteration":397,"passed_time":1.983205363,"remaining_time":2.999722685},
{"learn":[0.2156583807],"iteration":398,"passed_time":1.987372627,"remaining_time":2.993511151},
{"learn":[0.2155355361],"iteration":399,"passed_time":1.991982801,"remaining_time":2.987974202},
{"learn":[0.2153720816],"iteration":400,"passed_time":1.995970175,"remaining_time":2.981511558},
{"learn":[0.2151912059],"iteration":401,"passed_time":2.000158588,"remaining_time":2.975360288},
{"learn":[0.215015657],"iteration":402,"passed_time":2.005100063,"remaining_time":2.970334337},
{"learn":[0.214801911],"iteration":403,"passed_time":2.009154701,"remaining_time":2.9640005},
{"learn":[0.2146535212],"iteration":404,"passed_time":2.013244142,"remaining_time":2.957729048},
{"learn":[0.2144348418],"iteration":405,"passed_time":2.017338896,"remaining_time":2.951476119},
{"learn":[0.2142302407],"iteration":406,"passed_time":2.022117801,"remaining_time":2.946230604},
{"learn":[0.2140707379],"iteration":407,"passed_time":2.026686673,"remaining_time":2.940682623},
{"learn":[0.2139395817],"iteration":408,"passed_time":2.030713825,"remaining_time":2.934356652},
{"learn":[0.2137485222],"iteration":409,"passed_time":2.03476448,"remaining_time":2.928075715},
{"learn":[0.2136254599],"iteration":410,"passed_time":2.039790756,"remaining_time":2.923203784},
{"learn":[0.2133782297],"iteration":411,"passed_time":2.045631056,"remaining_time":2.919492866},
{"learn":[0.2132039643],"iteration":412,"passed_time":2.050189091,"remaining_time":2.913949144},
{"learn":[0.213040102],"iteration":413,"passed_time":2.055344292,"remaining_time":2.909255448},
{"learn":[0.2129244343],"iteration":414,"passed_time":2.059623845,"remaining_time":2.903325179},
{"learn":[0.2127610097],"iteration":415,"passed_time":2.063870649,"remaining_time":2.897356873},
{"learn":[0.2126488402],"iteration":416,"passed_time":2.067871604,"remaining_time":2.891053106},
{"learn":[0.2125255898],"iteration":417,"passed_time":2.073379247,"remaining_time":2.886858186},
{"learn":[0.2123944217],"iteration":418,"passed_time":2.077412789,"remaining_time":2.880612961},
{"learn":[0.2123030277],"iteration":419,"passed_time":2.081491511,"remaining_time":2.874440658},
{"learn":[0.212102065],"iteration":420,"passed_time":2.086880308,"remaining_time":2.870080043},
{"learn":[0.2118276328],"iteration":421,"passed_time":2.091109327,"remaining_time":2.864126045},
{"learn":[0.2116919028],"iteration":422,"passed_time":2.09515606,"remaining_time":2.857931553},
{"learn":[0.2115643753],"iteration":423,"passed_time":2.099018314,"remaining_time":2.851496578},
{"learn":[0.2110787351],"iteration":424,"passed_time":2.104164643,"remaining_time":2.846810988},
{"learn":[0.2108597206],"iteration":425,"passed_time":2.108265211,"remaining_time":2.840714158},
{"learn":[0.210661863],"iteration":426,"passed_time":2.112302091,"remaining_time":2.834541214},
{"learn":[0.2103952837],"iteration":427,"passed_time":2.116153696,"remaining_time":2.828130641},
{"learn":[0.2102263234],"iteration":428,"passed_time":2.1212627,"remaining_time":2.823405598},
{"learn":[0.2100203314],"iteration":429,"passed_time":2.126094439,"remaining_time":2.818311233},
{"learn":[0.2099066996],"iteration":430,"passed_time":2.130230651,"remaining_time":2.812299861},
{"learn":[0.2097817672],"iteration":431,"passed_time":2.134734402,"remaining_time":2.806780417},
{"learn":[0.2096434938],"iteration":432,"passed_time":2.139348644,"remaining_time":2.80141035},
{"learn":[0.2095746442],"iteration":433,"passed_time":2.143883841,"remaining_time":2.795940677},
{"learn":[0.2094925055],"iteration":434,"passed_time":2.148365389,"remaining_time":2.79040562},
{"learn":[0.2093686204],"iteration":435,"passed_time":2.153373716,"remaining_time":2.785556825},
{"learn":[0.209285022],"iteration":436,"passed_time":2.157628895,"remaining_time":2.779736998},
{"learn":[0.2091460304],"iteration":437,"passed_time":2.161693595,"remaining_time":2.77367991},
{"learn":[0.2089786387],"iteration":438,"passed_time":2.166251247,"remaining_time":2.768261844},
{"learn":[0.2087765413],"iteration":439,"passed_time":2.171528939,"remaining_time":2.763764105},
{"learn":[0.2086427382],"iteration":440,"passed_time":2.175967155,"remaining_time":2.758198729},
{"learn":[0.208431712],"iteration":441,"passed_time":2.180167774,"remaining_time":2.752338502},
{"learn":[0.2082363586],"iteration":442,"passed_time":2.185448919,"remaining_time":2.747844352},
{"learn":[0.2081230296],"iteration":443,"passed_time":2.189702681,"remaining_time":2.742060114},
{"learn":[0.2079796861],"iteration":444,"passed_time":2.193869779,"remaining_time":2.736174668},
{"learn":[0.2078517246],"iteration":445,"passed_time":2.198423369,"remaining_time":2.73077701},
{"learn":[0.2077301812],"iteration":446,"passed_time":2.203681165,"remaining_time":2.726254327},
{"learn":[0.2075987518],"iteration":447,"passed_time":2.207814542,"remaining_time":2.720342917},
{"learn":[0.2074569439],"iteration":448,"passed_time":2.211998622,"remaining_time":2.714501649},
{"learn":[0.2073241432],"iteration":449,"passed_time":2.216981662,"remaining_time":2.709644253},
{"learn":[0.2072292235],"iteration":450,"passed_time":2.221844357,"remaining_time":2.704639804},
{"learn":[0.207109882],"iteration":451,"passed_time":2.226361272,"remaining_time":2.699216764},
{"learn":[0.2069955818],"iteration":452,"passed_time":2.230549795,"remaining_time":2.693401188},
{"learn":[0.2068967698],"iteration":453,"passed_time":2.236108197,"remaining_time":2.689240254},
{"learn":[0.2067632322],"iteration":454,"passed_time":2.240256287,"remaining_time":2.683383904},
{"learn":[0.2066408701],"iteration":455,"passed_time":2.244504024,"remaining_time":2.677653924},
{"learn":[0.2065388202],"iteration":456,"passed_time":2.249481205,"remaining_time":2.672797143},
{"learn":[0.2064564717],"iteration":457,"passed_time":2.253633369,"remaining_time":2.666963507},
{"learn":[0.2063298876],"iteration":458,"passed_time":2.257809346,"remaining_time":2.661165264},
{"learn":[0.206127405],"iteration":459,"passed_time":2.261990571,"remaining_time":2.655380236},
{"learn":[0.2060113791],"iteration":460,"passed_time":2.266816295,"remaining_time":2.650355711},
{"learn":[0.2058992159],"iteration":461,"passed_time":2.270889874,"remaining_time":2.644456173},
{"learn":[0.2056146798],"iteration":462,"passed_time":2.275069702,"remaining_time":2.638687754},
{"learn":[0.2053660316],"iteration":463,"passed_time":2.279119829,"remaining_time":2.632776354},
{"learn":[0.2052541506],"iteration":464,"passed_time":2.284280051,"remaining_time":2.628150166},
{"learn":[0.2051507502],"iteration":465,"passed_time":2.288460737,"remaining_time":2.622399213},
{"learn":[0.2050691552],"iteration":466,"passed_time":2.292460421,"remaining_time":2.616448403},
{"learn":[0.2049714065],"iteration":467,"passed_time":2.296618584,"remaining_time":2.610686082},
{"learn":[0.2048663804],"iteration":468,"passed_time":2.302007353,"remaining_time":2.606323891},
{"learn":[0.2047150296],"iteration":469,"passed_time":2.306172852,"remaining_time":2.600577897},
{"learn":[0.2044790981],"iteration":470,"passed_time":2.310238994,"remaining_time":2.594727023},
{"learn":[0.2043540604],"iteration":471,"passed_time":2.315470414,"remaining_time":2.590187243},
{"learn":[0.2042293352],"iteration":472,"passed_time":2.319641189,"remaining_time":2.584462805},
{"learn":[0.2041203039],"iteration":473,"passed_time":2.323743759,"remaining_time":2.578669234},
{"learn":[0.2039304132],"iteration":474,"passed_time":2.327977107,"remaining_time":2.573027329},
{"learn":[0.2038348331],"iteration":475,"passed_time":2.332827767,"remaining_time":2.568070903},
{"learn":[0.2036494517],"iteration":476,"passed_time":2.337399005,"remaining_time":2.562808553},
{"learn":[0.2034439145],"iteration":477,"passed_time":2.34149194,"remaining_time":2.557026763},
{"learn":[0.2031726173],"iteration":478,"passed_time":2.345995875,"remaining_time":2.551699063},
{"learn":[0.2030558545],"iteration":479,"passed_time":2.351068327,"remaining_time":2.546990687},
{"learn":[0.2029343988],"iteration":480,"passed_time":2.35517226,"remaining_time":2.541235765},
{"learn":[0.2028204085],"iteration":481,"passed_time":2.359302975,"remaining_time":2.535516475},
{"learn":[0.2026839909],"iteration":482,"passed_time":2.364651298,"remaining_time":2.531107083},
{"learn":[0.2024706489],"iteration":483,"passed_time":2.369038606,"remaining_time":2.525669258},
{"learn":[0.2023404314],"iteration":484,"passed_time":2.373230638,"remaining_time":2.520028409},
{"learn":[0.2021787918],"iteration":485,"passed_time":2.377446215,"remaining_time":2.514418425},
{"learn":[0.2020653441],"iteration":486,"passed_time":2.382771701,"remaining_time":2.509983331},
{"learn":[0.2018844033],"iteration":487,"passed_time":2.386883857,"remaining_time":2.504271588},
{"learn":[0.2017770901],"iteration":488,"passed_time":2.390881822,"remaining_time":2.498447057},
{"learn":[0.2015855552],"iteration":489,"passed_time":2.395345963,"remaining_time":2.493115186},
{"learn":[0.2014078769],"iteration":490,"passed_time":2.40016934,"remaining_time":2.488159255},
{"learn":[0.2012724912],"iteration":491,"passed_time":2.404350962,"remaining_time":2.482541237},
{"learn":[0.2011641601],"iteration":492,"passed_time":2.408474225,"remaining_time":2.476869031},
{"learn":[0.2009894652],"iteration":493,"passed_time":2.413406942,"remaining_time":2.472032212},
{"learn":[0.200883731],"iteration":494,"passed_time":2.417875512,"remaining_time":2.466721482},
{"learn":[0.2004915332],"iteration":495,"passed_time":2.422007795,"remaining_time":2.461072437},
{"learn":[0.2003942766],"iteration":496,"passed_time":2.426267799,"remaining_time":2.455558759},
{"learn":[0.2002555372],"iteration":497,"passed_time":2.431918061,"remaining_time":2.451451539},
{"learn":[0.2001566671],"iteration":498,"passed_time":2.436101015,"remaining_time":2.445864947},
{"learn":[0.2000742069],"iteration":499,"passed_time":2.440195375,"remaining_time":2.440195375},
{"learn":[0.2000051242],"iteration":500,"passed_time":2.444542515,"remaining_time":2.434783863},
{"learn":[0.1998693109],"iteration":501,"passed_time":2.449443397,"remaining_time":2.429925919},
{"learn":[0.1997420602],"iteration":502,"passed_time":2.453661871,"remaining_time":2.424393538},
{"learn":[0.1995850484],"iteration":503,"passed_time":2.457666468,"remaining_time":2.418655889},
{"learn":[0.1994786861],"iteration":504,"passed_time":2.462642116,"remaining_time":2.413876926},
{"learn":[0.1992465747],"iteration":505,"passed_time":2.466860872,"remaining_time":2.408358243},
{"learn":[0.1991635297],"iteration":506,"passed_time":2.470994974,"remaining_time":2.402762371},
{"learn":[0.1990582049],"iteration":507,"passed_time":2.475145036,"remaining_time":2.397187712},
{"learn":[0.1989521586],"iteration":508,"passed_time":2.480260098,"remaining_time":2.392549525},
{"learn":[0.1988313364],"iteration":509,"passed_time":2.48439147,"remaining_time":2.386964354},
{"learn":[0.1987106855],"iteration":510,"passed_time":2.488570297,"remaining_time":2.381430284},
{"learn":[0.1985500644],"iteration":511,"passed_time":2.492777171,"remaining_time":2.375928241},
{"learn":[0.1983683288],"iteration":512,"passed_time":2.497781223,"remaining_time":2.371188023},
{"learn":[0.1982198122],"iteration":513,"passed_time":2.50224577,"remaining_time":2.365936662},
{"learn":[0.1980634812],"iteration":514,"passed_time":2.506348915,"remaining_time":2.360348008},
{"learn":[0.1978712454],"iteration":515,"passed_time":2.51154442,"remaining_time":2.355789727},
{"learn":[0.1977864237],"iteration":516,"passed_time":2.515648084,"remaining_time":2.350208945},
{"learn":[0.1976500496],"iteration":517,"passed_time":2.51990121,"remaining_time":2.34477294},
{"learn":[0.1975395264],"iteration":518,"passed_time":2.523889056,"remaining_time":2.339095638},
{"learn":[0.1974228578],"iteration":519,"passed_time":2.528879767,"remaining_time":2.334350554},
{"learn":[0.1973252127],"iteration":520,"passed_time":2.533156667,"remaining_time":2.32894826},
{"learn":[0.1972265565],"iteration":521,"passed_time":2.53722569,"remaining_time":2.323359923},
{"learn":[0.197134008],"iteration":522,"passed_time":2.541624375,"remaining_time":2.318078063},
{"learn":[0.1970272331],"iteration":523,"passed_time":2.546998415,"remaining_time":2.313685583},
{"learn":[0.1968882691],"iteration":524,"passed_time":2.551264255,"remaining_time":2.308286707},
{"learn":[0.1967295798],"iteration":525,"passed_time":2.55537156,"remaining_time":2.302749276},
{"learn":[0.1965962681],"iteration":526,"passed_time":2.560348323,"remaining_time":2.297997641},
{"learn":[0.1964742725],"iteration":527,"passed_time":2.564457623,"remaining_time":2.292469694},
{"learn":[0.1963385334],"iteration":528,"passed_time":2.568499886,"remaining_time":2.286887422},
{"learn":[0.1961904126],"iteration":529,"passed_time":2.572534585,"remaining_time":2.281304255},
{"learn":[0.1960650727],"iteration":530,"passed_time":2.577414438,"remaining_time":2.276473393},
{"learn":[0.1959544152],"iteration":531,"passed_time":2.581587767,"remaining_time":2.271020818},
{"learn":[0.1958705583],"iteration":532,"passed_time":2.585645266,"remaining_time":2.265471556},
{"learn":[0.195732538],"iteration":533,"passed_time":2.589810999,"remaining_time":2.260022332},
{"learn":[0.1955941157],"iteration":534,"passed_time":2.595049651,"remaining_time":2.255510444},
{"learn":[0.1955050049],"iteration":535,"passed_time":2.599011013,"remaining_time":2.24989013},
{"learn":[0.1953675175],"iteration":536,"passed_time":2.603050616,"remaining_time":2.244343454},
{"learn":[0.1952431929],"iteration":537,"passed_time":2.607221447,"remaining_time":2.238915071},
{"learn":[0.1951416979],"iteration":538,"passed_time":2.612418776,"remaining_time":2.234369305},
{"learn":[0.1948560768],"iteration":539,"passed_time":2.61652026,"remaining_time":2.228887629},
{"learn":[0.1947400527],"iteration":540,"passed_time":2.620613665,"remaining_time":2.2234042},
{"learn":[0.194641433],"iteration":541,"passed_time":2.625513998,"remaining_time":2.21860777},
{"learn":[0.1945271003],"iteration":542,"passed_time":2.629735492,"remaining_time":2.213239631},
{"learn":[0.1943961897],"iteration":543,"passed_time":2.633769189,"remaining_time":2.207718291},
{"learn":[0.1942914218],"iteration":544,"passed_time":2.638683178,"remaining_time":2.202937332},
{"learn":[0.194161309],"iteration":545,"passed_time":2.644057398,"remaining_time":2.198538569},
{"learn":[0.1939830756],"iteration":546,"passed_time":2.648638481,"remaining_time":2.1934794},
{"learn":[0.1938223578],"iteration":547,"passed_time":2.652702471,"remaining_time":2.187995469},
{"learn":[0.1936708542],"iteration":548,"passed_time":2.656930146,"remaining_time":2.182651177},
{"learn":[0.1935166674],"iteration":549,"passed_time":2.661703116,"remaining_time":2.177757095},
{"learn":[0.1934324775],"iteration":550,"passed_time":2.665712388,"remaining_time":2.172241129},
{"learn":[0.1932855205],"iteration":551,"passed_time":2.669916345,"remaining_time":2.166888628},
{"learn":[0.1932247527],"iteration":552,"passed_time":2.674284103,"remaining_time":2.161672684},
{"learn":[0.1931208496],"iteration":553,"passed_time":2.678658697,"remaining_time":2.156465305},
{"learn":[0.1930019003],"iteration":554,"passed_time":2.682830176,"remaining_time":2.151098069},
{"learn":[0.1928793709],"iteration":555,"passed_time":2.686996484,"remaining_time":2.145731005},
{"learn":[0.1927510249],"iteration":556,"passed_time":2.692179946,"remaining_time":2.141177228},
{"learn":[0.1926958085],"iteration":557,"passed_time":2.696167662,"remaining_time":2.135674026},
{"learn":[0.1926184249],"iteration":558,"passed_time":2.70022881,"remaining_time":2.130234177},
{"learn":[0.1925351374],"iteration":559,"passed_time":2.70429815,"remaining_time":2.124805689},
{"learn":[0.1923512544],"iteration":560,"passed_time":2.709636102,"remaining_time":2.120374775},
{"learn":[0.1922084962],"iteration":561,"passed_time":2.713787158,"remaining_time":2.115015614},
{"learn":[0.1920470493],"iteration":562,"passed_time":2.717919264,"remaining_time":2.109646036},
{"learn":[0.1919077076],"iteration":563,"passed_time":2.722198267,"remaining_time":2.104394405},
{"learn":[0.1917532955],"iteration":564,"passed_time":2.727564522,"remaining_time":2.099983305},
{"learn":[0.191570149],"iteration":565,"passed_time":2.731638719,"remaining_time":2.094578099},
{"learn":[0.1914153932],"iteration":566,"passed_time":2.735843064,"remaining_time":2.089276978},
{"learn":[0.1913114323],"iteration":567,"passed_time":2.741056011,"remaining_time":2.084746825},
{"learn":[0.191216449],"iteration":568,"passed_time":2.745451087,"remaining_time":2.07959476},
{"learn":[0.1911380683],"iteration":569,"passed_time":2.749446341,"remaining_time":2.074143731},
{"learn":[0.190965807],"iteration":570,"passed_time":2.753620757,"remaining_time":2.068832408},
{"learn":[0.1908777552],"iteration":571,"passed_time":2.759324299,"remaining_time":2.064669231},
{"learn":[0.1907240658],"iteration":572,"passed_time":2.763854074,"remaining_time":2.059625985},
{"learn":[0.1904543986],"iteration":573,"passed_time":2.768014232,"remaining_time":2.054310214},
{"learn":[0.1903256137],"iteration":574,"passed_time":2.772945266,"remaining_time":2.04956824},
{"learn":[0.1901519623],"iteration":575,"passed_time":2.777287122,"remaining_time":2.044391909},
{"learn":[0.1900727576],"iteration":576,"passed_time":2.781373947,"remaining_time":2.039031507},
{"learn":[0.1899379988],"iteration":577,"passed_time":2.785441406,"remaining_time":2.033661373},
{"learn":[0.1898343678],"iteration":578,"passed_time":2.79075306,"remaining_time":2.029200412},
{"learn":[0.1897484621],"iteration":579,"passed_time":2.795183614,"remaining_time":2.024098479},
{"learn":[0.1896634778],"iteration":580,"passed_time":2.799212374,"remaining_time":2.018709096},
{"learn":[0.1895807433],"iteration":581,"passed_time":2.803360656,"remaining_time":2.01341023},
{"learn":[0.1894610437],"iteration":582,"passed_time":2.808460506,"remaining_time":2.008795937},
{"learn":[0.1893445583],"iteration":583,"passed_time":2.812595718,"remaining_time":2.00349284},
{"learn":[0.1892651608],"iteration":584,"passed_time":2.816715683,"remaining_time":1.99818292},
{"learn":[0.1891395949],"iteration":585,"passed_time":2.821930087,"remaining_time":1.993650267},
{"learn":[0.1890702959],"iteration":586,"passed_time":2.826069161,"remaining_time":1.988358712},
{"learn":[0.1889508513],"iteration":587,"passed_time":2.830186585,"remaining_time":1.983055906},
{"learn":[0.1888204314],"iteration":588,"passed_time":2.834344923,"remaining_time":1.977785676},
{"learn":[0.1886721904],"iteration":589,"passed_time":2.839503995,"remaining_time":1.973214641},
{"learn":[0.1886233095],"iteration":590,"passed_time":2.843614672,"remaining_time":1.967916076},
{"learn":[0.1884556914],"iteration":591,"passed_time":2.8478652,"remaining_time":1.962717908},
{"learn":[0.1883360988],"iteration":592,"passed_time":2.852006177,"remaining_time":1.957447747},
{"learn":[0.1881922103],"iteration":593,"passed_time":2.857808214,"remaining_time":1.953316725},
{"learn":[0.1881057088],"iteration":594,"passed_time":2.861992444,"remaining_time":1.94807889},
{"learn":[0.1879706128],"iteration":595,"passed_time":2.866042305,"remaining_time":1.942753509},
{"learn":[0.1876393358],"iteration":596,"passed_time":2.871182608,"remaining_time":1.938168494},
{"learn":[0.1875401522],"iteration":597,"passed_time":2.875478467,"remaining_time":1.933013952},
{"learn":[0.1874262515],"iteration":598,"passed_time":2.879559399,"remaining_time":1.927718396},
{"learn":[0.1873340261],"iteration":599,"passed_time":2.883751132,"remaining_time":1.922500755},
{"learn":[0.1872491964],"iteration":600,"passed_time":2.888807924,"remaining_time":1.917860835},
{"learn":[0.1871513717],"iteration":601,"passed_time":2.89292855,"remaining_time":1.912600603},
{"learn":[0.1870338495],"iteration":602,"passed_time":2.897060323,"remaining_time":1.90735149},
{"learn":[0.1869381857],"iteration":603,"passed_time":2.901177294,"remaining_time":1.902096371},
{"learn":[0.1868009471],"iteration":604,"passed_time":2.906365951,"remaining_time":1.897544712},
{"learn":[0.1866912474],"iteration":605,"passed_time":2.910830336,"remaining_time":1.892520054},
{"learn":[0.1865956891],"iteration":606,"passed_time":2.914931897,"remaining_time":1.887262332},
{"learn":[0.1864632171],"iteration":607,"passed_time":2.919765052,"remaining_time":1.882480099},
{"learn":[0.1863125625],"iteration":608,"passed_time":2.924169254,"remaining_time":1.877422296},
{"learn":[0.1861796042],"iteration":609,"passed_time":2.928757976,"remaining_time":1.872484608},
{"learn":[0.1860678267],"iteration":610,"passed_time":2.933145061,"remaining_time":1.867419687},
{"learn":[0.1859829536],"iteration":611,"passed_time":2.938697226,"remaining_time":1.863095627},
{"learn":[0.185872177],"iteration":612,"passed_time":2.942971864,"remaining_time":1.85796103},
{"learn":[0.1857808155],"iteration":613,"passed_time":2.947138079,"remaining_time":1.852761073},
{"learn":[0.1856778137],"iteration":614,"passed_time":2.952066874,"remaining_time":1.848041864},
{"learn":[0.1854914697],"iteration":615,"passed_time":2.956526977,"remaining_time":1.843029804},
{"learn":[0.1853646829],"iteration":616,"passed_time":2.960805521,"remaining_time":1.837906831},
{"learn":[0.1852651939],"iteration":617,"passed_time":2.964932863,"remaining_time":1.832693129},
{"learn":[0.1851450155],"iteration":618,"passed_time":2.970058617,"remaining_time":1.828097469},
{"learn":[0.1850588362],"iteration":619,"passed_time":2.97553773,"remaining_time":1.823716673},
{"learn":[0.1849659034],"iteration":620,"passed_time":2.980343576,"remaining_time":1.818921442},
{"learn":[0.1847862584],"iteration":621,"passed_time":2.985702041,"remaining_time":1.814462012},
{"learn":[0.1847072478],"iteration":622,"passed_time":2.989986912,"remaining_time":1.809350025},
{"learn":[0.1845578388],"iteration":623,"passed_time":2.994299422,"remaining_time":1.804257344},
{"learn":[0.1844243014],"iteration":624,"passed_time":2.99868099,"remaining_time":1.799208594},
{"learn":[0.184334311],"iteration":625,"passed_time":3.004325357,"remaining_time":1.794916427},
{"learn":[0.1842583247],"iteration":626,"passed_time":3.009031922,"remaining_time":1.790062053},
{"learn":[0.1841608838],"iteration":627,"passed_time":3.013492517,"remaining_time":1.785062446},
{"learn":[0.1840073828],"iteration":628,"passed_time":3.01852278,"remaining_time":1.780400559},
{"learn":[0.1838621266],"iteration":629,"passed_time":3.02273323,"remaining_time":1.775256024},
{"learn":[0.1837759375],"iteration":630,"passed_time":3.0267969,"remaining_time":1.770028615},
{"learn":[0.1837213309],"iteration":631,"passed_time":3.031363186,"remaining_time":1.765097551},
{"learn":[0.1836278852],"iteration":632,"passed_time":3.036722794,"remaining_time":1.760627591},
{"learn":[0.1835266494],"iteration":633,"passed_time":3.040989158,"remaining_time":1.75552371},
{"learn":[0.1834322844],"iteration":634,"passed_time":3.045200618,"remaining_time":1.750390906},
{"learn":[0.183362043],"iteration":635,"passed_time":3.049784183,"remaining_time":1.745473966},
{"learn":[0.1832582024],"iteration":636,"passed_time":3.054383418,"remaining_time":1.740567003},
{"learn":[0.18318506],"iteration":637,"passed_time":3.058455649,"remaining_time":1.735361983},
{"learn":[0.1830837497],"iteration":638,"passed_time":3.062676431,"remaining_time":1.730244431},
{"learn":[0.1828949029],"iteration":639,"passed_time":3.067691316,"remaining_time":1.725576365},
{"learn":[0.182808381],"iteration":640,"passed_time":3.072240734,"remaining_time":1.720646526},
{"learn":[0.1827011631],"iteration":641,"passed_time":3.07634281,"remaining_time":1.715468421},
{"learn":[0.1826102808],"iteration":642,"passed_time":3.080583089,"remaining_time":1.710370393},
{"learn":[0.1825519184],"iteration":643,"passed_time":3.085835839,"remaining_time":1.705834719},
{"learn":[0.1824425451],"iteration":644,"passed_time":3.090090388,"remaining_time":1.700747423},
{"learn":[0.1823585919],"iteration":645,"passed_time":3.094041224,"remaining_time":1.695496275},
{"learn":[0.1822604698],"iteration":646,"passed_time":3.098680117,"remaining_time":1.690624546},
{"learn":[0.1821597428],"iteration":647,"passed_time":3.103197506,"remaining_time":1.685687534},
{"learn":[0.1820439942],"iteration":648,"passed_time":3.107244401,"remaining_time":1.680497357},
{"learn":[0.1819568042],"iteration":649,"passed_time":3.111373741,"remaining_time":1.675355091},
{"learn":[0.1818391086],"iteration":650,"passed_time":3.116502087,"remaining_time":1.670751503},
{"learn":[0.1817660073],"iteration":651,"passed_time":3.120799685,"remaining_time":1.6657029},
{"learn":[0.181691763],"iteration":652,"passed_time":3.125013979,"remaining_time":1.660612329},
{"learn":[0.1815713754],"iteration":653,"passed_time":3.129763354,"remaining_time":1.655807524},
{"learn":[0.1814252954],"iteration":654,"passed_time":3.135215397,"remaining_time":1.651372995},
{"learn":[0.1813558139],"iteration":655,"passed_time":3.139315381,"remaining_time":1.646226358},
{"learn":[0.181283969],"iteration":656,"passed_time":3.143372815,"remaining_time":1.641060693},
{"learn":[0.1811570686],"iteration":657,"passed_time":3.148068605,"remaining_time":1.636230187},
{"learn":[0.1810789408],"iteration":658,"passed_time":3.152661593,"remaining_time":1.631346894},
{"learn":[0.1810086361],"iteration":659,"passed_time":3.15679173,"remaining_time":1.626226043},
{"learn":[0.180920082],"iteration":660,"passed_time":3.161133048,"remaining_time":1.621216495},
{"learn":[0.1807912474],"iteration":661,"passed_time":3.166714495,"remaining_time":1.616842144},
{"learn":[0.1806860962],"iteration":662,"passed_time":3.170978437,"remaining_time":1.611794469},
{"learn":[0.1806108409],"iteration":663,"passed_time":3.175130229,"remaining_time":1.606692405},
{"learn":[0.1804989983],"iteration":664,"passed_time":3.180134536,"remaining_time":1.602022661},
{"learn":[0.1802482168],"iteration":665,"passed_time":3.184944988,"remaining_time":1.597254694},
{"learn":[0.1801610941],"iteration":666,"passed_time":3.188999429,"remaining_time":1.59210916},
{"learn":[0.1800340959],"iteration":667,"passed_time":3.193031756,"remaining_time":1.586955902},
{"learn":[0.1799092789],"iteration":668,"passed_time":3.19826053,"remaining_time":1.58239796},
{"learn":[0.1798455985],"iteration":669,"passed_time":3.202266793,"remaining_time":1.577235883},
{"learn":[0.1797236056],"iteration":670,"passed_time":3.206412824,"remaining_time":1.572145781},
{"learn":[0.1796039481],"iteration":671,"passed_time":3.210570302,"remaining_time":1.567064076},
{"learn":[0.1794556482],"iteration":672,"passed_time":3.215852263,"remaining_time":1.562531486},
{"learn":[0.1793462443],"iteration":673,"passed_time":3.219837736,"remaining_time":1.557369587},
{"learn":[0.1792593759],"iteration":674,"passed_time":3.223918516,"remaining_time":1.552257063},
{"learn":[0.1790814763],"iteration":675,"passed_time":3.228246076,"remaining_time":1.547265871},
{"learn":[0.1790079018],"iteration":676,"passed_time":3.233362229,"remaining_time":1.54265288},
{"learn":[0.1789234402],"iteration":677,"passed_time":3.237520611,"remaining_time":1.537583535},
{"learn":[0.178845244],"iteration":678,"passed_time":3.241694212,"remaining_time":1.532524068},
{"learn":[0.1787815147],"iteration":679,"passed_time":3.247106582,"remaining_time":1.528050156},
{"learn":[0.1787091995],"iteration":680,"passed_time":3.251175868,"remaining_time":1.522944349},
{"learn":[0.1786026071],"iteration":681,"passed_time":3.255353204,"remaining_time":1.517891963},
{"learn":[0.1785161927],"iteration":682,"passed_time":3.259472352,"remaining_time":1.512815133},
{"learn":[0.1783558583],"iteration":683,"passed_time":3.265258676,"remaining_time":1.508511318},
{"learn":[0.1782375201],"iteration":684,"passed_time":3.269274827,"remaining_time":1.503389154},
{"learn":[0.1781442778],"iteration":685,"passed_time":3.273334902,"remaining_time":1.49829032},
{"learn":[0.1780525682],"iteration":686,"passed_time":3.278197306,"remaining_time":1.493560054},
{"learn":[0.1779830706],"iteration":687,"passed_time":3.283201698,"remaining_time":1.488893793},
{"learn":[0.1778660945],"iteration":688,"passed_time":3.287355771,"remaining_time":1.483842736},
{"learn":[0.1777588871],"iteration":689,"passed_time":3.291414353,"remaining_time":1.478751376},
{"learn":[0.1776549522],"iteration":690,"passed_time":3.29696908,"remaining_time":1.474332049},
{"learn":[0.1775849757],"iteration":691,"passed_time":3.30108818,"remaining_time":1.469270462},
{"learn":[0.1774272762],"iteration":692,"passed_time":3.30518705,"remaining_time":1.464202633},
{"learn":[0.1773508412],"iteration":693,"passed_time":3.309246952,"remaining_time":1.459120414},
{"learn":[0.177284958],"iteration":694,"passed_time":3.314472558,"remaining_time":1.454552705},
{"learn":[0.1771879826],"iteration":695,"passed_time":3.318545858,"remaining_time":1.4494798},
{"learn":[0.1771163646],"iteration":696,"passed_time":3.322555879,"remaining_time":1.444382254},
{"learn":[0.1770501493],"iteration":697,"passed_time":3.328114413,"remaining_time":1.439957812},
{"learn":[0.1769864029],"iteration":698,"passed_time":3.333139394,"remaining_time":1.435300368},
{"learn":[0.1768574736],"iteration":699,"passed_time":3.337428205,"remaining_time":1.430326374},
{"learn":[0.1767567851],"iteration":700,"passed_time":3.341436036,"remaining_time":1.425234486},
{"learn":[0.1766502507],"iteration":701,"passed_time":3.347140899,"remaining_time":1.420866079},
{"learn":[0.1765696197],"iteration":702,"passed_time":3.351126143,"remaining_time":1.415767375},
{"learn":[0.1764459426],"iteration":703,"passed_time":3.355254148,"remaining_time":1.410731857},
{"learn":[0.1763386897],"iteration":704,"passed_time":3.360955538,"remaining_time":1.406357282},
{"learn":[0.1762589589],"iteration":705,"passed_time":3.36509676,"remaining_time":1.401329246},
{"learn":[0.1761296856],"iteration":706,"passed_time":3.369317331,"remaining_time":1.396336603},
{"learn":[0.1760519163],"iteration":707,"passed_time":3.373522765,"remaining_time":1.391339897},
{"learn":[0.175979283],"iteration":708,"passed_time":3.378759759,"remaining_time":1.386768815},
{"learn":[0.1757790928],"iteration":709,"passed_time":3.383277182,"remaining_time":1.381901948},
{"learn":[0.1757166116],"iteration":710,"passed_time":3.38740922,"remaining_time":1.376879416},
{"learn":[0.175551143],"iteration":711,"passed_time":3.391934833,"remaining_time":1.372018584},
{"learn":[0.1754727113],"iteration":712,"passed_time":3.396660884,"remaining_time":1.367239374},
{"learn":[0.1753210847],"iteration":713,"passed_time":3.400899355,"remaining_time":1.362265008},
{"learn":[0.1752426981],"iteration":714,"passed_time":3.405173398,"remaining_time":1.357306879},
{"learn":[0.1751407402],"iteration":715,"passed_time":3.410560743,"remaining_time":1.35279225},
{"learn":[0.1750691319],"iteration":716,"passed_time":3.414708194,"remaining_time":1.347785801},
{"learn":[0.1749973184],"iteration":717,"passed_time":3.418974712,"remaining_time":1.342828508},
{"learn":[0.1749070678],"iteration":718,"passed_time":3.423129776,"remaining_time":1.337829579},
{"learn":[0.1748324541],"iteration":719,"passed_time":3.428989829,"remaining_time":1.333496045},
{"learn":[0.1747073366],"iteration":720,"passed_time":3.433500588,"remaining_time":1.32863615},
{"learn":[0.1745930609],"iteration":721,"passed_time":3.437642067,"remaining_time":1.323635034},
{"learn":[0.1745157608],"iteration":722,"passed_time":3.44232416,"remaining_time":1.31884342},
{"learn":[0.1744639471],"iteration":723,"passed_time":3.44655681,"remaining_time":1.313880773},
{"learn":[0.1743285098],"iteration":724,"passed_time":3.450844757,"remaining_time":1.308941115},
{"learn":[0.1742223164],"iteration":725,"passed_time":3.454921897,"remaining_time":1.303923691},
{"learn":[0.1741666651],"iteration":726,"passed_time":3.460027449,"remaining_time":1.299295039},
{"learn":[0.1740723599],"iteration":727,"passed_time":3.464245646,"remaining_time":1.294333538},
{"learn":[0.1739634573],"iteration":728,"passed_time":3.468332513,"remaining_time":1.289325255},
{"learn":[0.1738595133],"iteration":729,"passed_time":3.472559252,"remaining_time":1.28437123},
{"learn":[0.1737594798],"iteration":730,"passed_time":3.478024438,"remaining_time":1.27987493},
{"learn":[0.1736969676],"iteration":731,"passed_time":3.482399294,"remaining_time":1.274976791},
{"learn":[0.1736152369],"iteration":732,"passed_time":3.486516167,"remaining_time":1.269986107},
{"learn":[0.1735082426],"iteration":733,"passed_time":3.491575953,"remaining_time":1.265339514},
{"learn":[0.1734464302],"iteration":734,"passed_time":3.496294632,"remaining_time":1.260568813},
{"learn":[0.173340137],"iteration":735,"passed_time":3.500681219,"remaining_time":1.255679133},
{"learn":[0.1732343952],"iteration":736,"passed_time":3.504720771,"remaining_time":1.250666978},
{"learn":[0.1731108047],"iteration":737,"passed_time":3.510259675,"remaining_time":1.246189749},
{"learn":[0.1730054728],"iteration":738,"passed_time":3.514677776,"remaining_time":1.241313802},
{"learn":[0.1729410709],"iteration":739,"passed_time":3.519145306,"remaining_time":1.236456459},
{"learn":[0.1728740472],"iteration":740,"passed_time":3.525468803,"remaining_time":1.23224888},
{"learn":[0.1727890413],"iteration":741,"passed_time":3.530225301,"remaining_time":1.227490738},
{"learn":[0.1727226067],"iteration":742,"passed_time":3.534984999,"remaining_time":1.222733707},
{"learn":[0.1726339538],"iteration":743,"passed_time":3.540466936,"remaining_time":1.218225182},
{"learn":[0.1725769058],"iteration":744,"passed_time":3.545057288,"remaining_time":1.21340887},
{"learn":[0.1725032409],"iteration":745,"passed_time":3.549189994,"remaining_time":1.208437344},
{"learn":[0.172415165],"iteration":746,"passed_time":3.553297191,"remaining_time":1.203459423},
{"learn":[0.1723114435],"iteration":747,"passed_time":3.559370294,"remaining_time":1.199146142},
{"learn":[0.1722594038],"iteration":748,"passed_time":3.564041213,"remaining_time":1.19435827},
{"learn":[0.1721858685],"iteration":749,"passed_time":3.568294058,"remaining_time":1.189431353},
{"learn":[0.1721180932],"iteration":750,"passed_time":3.573355209,"remaining_time":1.18477423},
{"learn":[0.1720508082],"iteration":751,"passed_time":3.578284953,"remaining_time":1.180072697},
{"learn":[0.1719606113],"iteration":752,"passed_time":3.582379973,"remaining_time":1.175096751},
{"learn":[0.1718961568],"iteration":753,"passed_time":3.58659533,"remaining_time":1.170162402},
{"learn":[0.1717759765],"iteration":754,"passed_time":3.59267228,"remaining_time":1.165834051},
{"learn":[0.1716934694],"iteration":755,"passed_time":3.596893008,"remaining_time":1.160901976},
{"learn":[0.1716220617],"iteration":756,"passed_time":3.601051035,"remaining_time":1.155951653},
{"learn":[0.1715508673],"iteration":757,"passed_time":3.605850691,"remaining_time":1.151208268},
{"learn":[0.1714226224],"iteration":758,"passed_time":3.61003008,"remaining_time":1.146267786},
{"learn":[0.1712975105],"iteration":759,"passed_time":3.614186192,"remaining_time":1.141321955},
{"learn":[0.171222273],"iteration":760,"passed_time":3.618578812,"remaining_time":1.136452478},
{"learn":[0.1711458256],"iteration":761,"passed_time":3.624496476,"remaining_time":1.132060579},
{"learn":[0.1710342429],"iteration":762,"passed_time":3.628824916,"remaining_time":1.127171042},
{"learn":[0.1709705017],"iteration":763,"passed_time":3.633102567,"remaining_time":1.122267285},
{"learn":[0.1708620307],"iteration":764,"passed_time":3.638229449,"remaining_time":1.11762604},
{"learn":[0.170740121],"iteration":765,"passed_time":3.6427527,"remaining_time":1.112799128},
{"learn":[0.1706775051],"iteration":766,"passed_time":3.647004371,"remaining_time":1.107890507},
{"learn":[0.170617067],"iteration":767,"passed_time":3.651046022,"remaining_time":1.102920152},
{"learn":[0.1705331603],"iteration":768,"passed_time":3.656308029,"remaining_time":1.098318797},
{"learn":[0.1704043758],"iteration":769,"passed_time":3.660421805,"remaining_time":1.093372747},
{"learn":[0.1703093075],"iteration":770,"passed_time":3.664561418,"remaining_time":1.08843653},
{"learn":[0.1702202614],"iteration":771,"passed_time":3.66869913,"remaining_time":1.083501816},
{"learn":[0.1701607801],"iteration":772,"passed_time":3.674041621,"remaining_time":1.07892296},
{"learn":[0.1700730732],"iteration":773,"passed_time":3.678204882,"remaining_time":1.073997808},
{"learn":[0.1700024647],"iteration":774,"passed_time":3.682199225,"remaining_time":1.069025581},
{"learn":[0.1699322012],"iteration":775,"passed_time":3.686702631,"remaining_time":1.064202821},
{"learn":[0.1698514674],"iteration":776,"passed_time":3.691860055,"remaining_time":1.059568587},
{"learn":[0.1697516483],"iteration":777,"passed_time":3.696436068,"remaining_time":1.054767104},
{"learn":[0.1696726747],"iteration":778,"passed_time":3.700376737,"remaining_time":1.049785955},
{"learn":[0.1695347919],"iteration":779,"passed_time":3.705388085,"remaining_time":1.04510946},
{"learn":[0.1694243675],"iteration":780,"passed_time":3.709631485,"remaining_time":1.040216767},
{"learn":[0.1693463785],"iteration":781,"passed_time":3.713958345,"remaining_time":1.035349002},
{"learn":[0.1692777787],"iteration":782,"passed_time":3.718122198,"remaining_time":1.030437442},
{"learn":[0.1692368598],"iteration":783,"passed_time":3.72378658,"remaining_time":1.025941201},
{"learn":[0.169177824],"iteration":784,"passed_time":3.728014764,"remaining_time":1.02104863},
{"learn":[0.1691117871],"iteration":785,"passed_time":3.732620097,"remaining_time":1.016260434},
{"learn":[0.169023351],"iteration":786,"passed_time":3.73751592,"remaining_time":1.011551323},
{"learn":[0.1689477169],"iteration":787,"passed_time":3.741667615,"remaining_time":1.006641541},
{"learn":[0.1688452013],"iteration":788,"passed_time":3.74577901,"remaining_time":1.001722904},
{"learn":[0.1687836432],"iteration":789,"passed_time":3.749990694,"remaining_time":0.9968329694},
{"learn":[0.168717742],"iteration":790,"passed_time":3.755172076,"remaining_time":0.9922009657},
{"learn":[0.1686137393],"iteration":791,"passed_time":3.759256878,"remaining_time":0.9872795841},
{"learn":[0.1685368201],"iteration":792,"passed_time":3.76332543,"remaining_time":0.9823560707},
{"learn":[0.1684445351],"iteration":793,"passed_time":3.767898521,"remaining_time":0.9775656113},
{"learn":[0.1683619925],"iteration":794,"passed_time":3.772625318,"remaining_time":0.9728153335},
{"learn":[0.1682738513],"iteration":795,"passed_time":3.776667988,"remaining_time":0.9678897859},
{"learn":[0.1681771944],"iteration":796,"passed_time":3.780706907,"remaining_time":0.9629654982},
{"learn":[0.1680746865],"iteration":797,"passed_time":3.785727576,"remaining_time":0.9582919428},
{"learn":[0.1679980404],"iteration":798,"passed_time":3.790091615,"remaining_time":0.9534523336},
{"learn":[0.1679073554],"iteration":799,"passed_time":3.794298357,"remaining_time":0.9485745892},
{"learn":[0.1678303473],"iteration":800,"passed_time":3.798327576,"remaining_time":0.9436544165},
{"learn":[0.1677401893],"iteration":801,"passed_time":3.803565687,"remaining_time":0.9390349203},
{"learn":[0.1676730142],"iteration":802,"passed_time":3.807800462,"remaining_time":0.9341677349},
{"learn":[0.1676082617],"iteration":803,"passed_time":3.8117677,"remaining_time":0.929236902},
{"learn":[0.1675240687],"iteration":804,"passed_time":3.815829557,"remaining_time":0.9243313835},
{"learn":[0.1674482131],"iteration":805,"passed_time":3.821215457,"remaining_time":0.9197466485},
{"learn":[0.167361497],"iteration":806,"passed_time":3.825526323,"remaining_time":0.9149028257},
{"learn":[0.167312602],"iteration":807,"passed_time":3.829773423,"remaining_time":0.9100451699},
{"learn":[0.1671778284],"iteration":808,"passed_time":3.834923629,"remaining_time":0.9054022413},
{"learn":[0.1671058165],"iteration":809,"passed_time":3.839095018,"remaining_time":0.900528461},
{"learn":[0.1669886019],"iteration":810,"passed_time":3.843165053,"remaining_time":0.8956327928},
{"learn":[0.1668895939],"iteration":811,"passed_time":3.847460644,"remaining_time":0.8907913807},
{"learn":[0.1668177083],"iteration":812,"passed_time":3.85270763,"remaining_time":0.8861701436},
{"learn":[0.1667576619],"iteration":813,"passed_time":3.856738539,"remaining_time":0.8812694943},
{"learn":[0.1666669989],"iteration":814,"passed_time":3.860834405,"remaining_time":0.8763857239},
{"learn":[0.1666017046],"iteration":815,"passed_time":3.864886844,"remaining_time":0.8714940923},
{"learn":[0.1665484061],"iteration":816,"passed_time":3.870059262,"remaining_time":0.8668553794},
{"learn":[0.1664797202],"iteration":817,"passed_time":3.874156675,"remaining_time":0.8619761796},
{"learn":[0.1662683741],"iteration":818,"passed_time":3.878260962,"remaining_time":0.857100408},
{"learn":[0.1662318318],"iteration":819,"passed_time":3.882865391,"remaining_time":0.8523363054},
{"learn":[0.166104835],"iteration":820,"passed_time":3.887484153,"remaining_time":0.8475757166},
{"learn":[0.1660102209],"iteration":821,"passed_time":3.891848588,"remaining_time":0.8427603998},
{"learn":[0.1659320068],"iteration":822,"passed_time":3.895919931,"remaining_time":0.8378831444},
{"learn":[0.165860701],"iteration":823,"passed_time":3.900834343,"remaining_time":0.833187918},
{"learn":[0.165768424],"iteration":824,"passed_time":3.905315819,"remaining_time":0.8284003252},
{"learn":[0.1657283505],"iteration":825,"passed_time":3.909743879,"remaining_time":0.8236022215},
{"learn":[0.1656603763],"iteration":826,"passed_time":3.914729155,"remaining_time":0.8189215765},
{"learn":[0.1655862757],"iteration":827,"passed_time":3.919733446,"remaining_time":0.8142441458},
{"learn":[0.1655191457],"iteration":828,"passed_time":3.924404333,"remaining_time":0.8094971543},
{"learn":[0.1654545654],"iteration":829,"passed_time":3.928476944,"remaining_time":0.8046278077},
{"learn":[0.1653556821],"iteration":830,"passed_time":3.934410223,"remaining_time":0.8001387817},
{"learn":[0.1652986948],"iteration":831,"passed_time":3.939079663,"remaining_time":0.7953910858},
{"learn":[0.1652052322],"iteration":832,"passed_time":3.9432261,"remaining_time":0.790538726},
{"learn":[0.1651369252],"iteration":833,"passed_time":3.948305185,"remaining_time":0.785873694},
{"learn":[0.1650571693],"iteration":834,"passed_time":3.953334068,"remaining_time":0.7811977499},
{"learn":[0.1649585002],"iteration":835,"passed_time":3.958055007,"remaining_time":0.7764605516},
{"learn":[0.1648967546],"iteration":836,"passed_time":3.962317502,"remaining_time":0.7716341133},
{"learn":[0.1648039304],"iteration":837,"passed_time":3.967799644,"remaining_time":0.7670447999},
{"learn":[0.1646759924],"iteration":838,"passed_time":3.972623332,"remaining_time":0.7623270041},
{"learn":[0.1645891331],"iteration":839,"passed_time":3.976712405,"remaining_time":0.7574690296},
{"learn":[0.1645101031],"iteration":840,"passed_time":3.981972558,"remaining_time":0.7528342886},
{"learn":[0.1644303002],"iteration":841,"passed_time":3.98663293,"remaining_time":0.7480855142},
{"learn":[0.1643590865],"iteration":842,"passed_time":3.990928903,"remaining_time":0.7432690839},
{"learn":[0.1642695757],"iteration":843,"passed_time":3.995121006,"remaining_time":0.7384346882},
{"learn":[0.1641497343],"iteration":844,"passed_time":4.001446707,"remaining_time":0.7339931829},
{"learn":[0.1640563471],"iteration":845,"passed_time":4.005644806,"remaining_time":0.7291599292},
{"learn":[0.1639968552],"iteration":846,"passed_time":4.009677252,"remaining_time":0.7242982521},
{"learn":[0.1639272178],"iteration":847,"passed_time":4.015149082,"remaining_time":0.7196965336},
{"learn":[0.1638093386],"iteration":848,"passed_time":4.020618475,"remaining_time":0.7150923318},
{"learn":[0.1637027834],"iteration":849,"passed_time":4.024969301,"remaining_time":0.7102887002},
{"learn":[0.1636193876],"iteration":850,"passed_time":4.030003545,"remaining_time":0.7056057911},
{"learn":[0.1635299868],"iteration":851,"passed_time":4.034358148,"remaining_time":0.7008039975},
{"learn":[0.1634700944],"iteration":852,"passed_time":4.039738001,"remaining_time":0.6961799369},
{"learn":[0.1633190758],"iteration":853,"passed_time":4.043949458,"remaining_time":0.691354357},
{"learn":[0.1632348196],"iteration":854,"passed_time":4.048006063,"remaining_time":0.6865039522},
{"learn":[0.1631798409],"iteration":855,"passed_time":4.053072156,"remaining_time":0.6818252226},
{"learn":[0.1631235194],"iteration":856,"passed_time":4.057446727,"remaining_time":0.6770302006},
{"learn":[0.1630509355],"iteration":857,"passed_time":4.061677585,"remaining_time":0.6722123742},
{"learn":[0.1629975783],"iteration":858,"passed_time":4.066074856,"remaining_time":0.6674232302},
{"learn":[0.1629318812],"iteration":859,"passed_time":4.071041713,"remaining_time":0.6627277207},
{"learn":[0.1627867947],"iteration":860,"passed_time":4.075450303,"remaining_time":0.6579414543},
{"learn":[0.1627214521],"iteration":861,"passed_time":4.079591515,"remaining_time":0.6531132587},
{"learn":[0.1626579755],"iteration":862,"passed_time":4.083802489,"remaining_time":0.64829773},
{"learn":[0.162574142],"iteration":863,"passed_time":4.088984615,"remaining_time":0.6436364673},
{"learn":[0.1623627317],"iteration":864,"passed_time":4.093135592,"remaining_time":0.6388130693},
{"learn":[0.1622818123],"iteration":865,"passed_time":4.097289211,"remaining_time":0.6339916331},
{"learn":[0.1622027045],"iteration":866,"passed_time":4.102559244,"remaining_time":0.6293429981},
{"learn":[0.1620741209],"iteration":867,"passed_time":4.107743974,"remaining_time":0.6246799592},
{"learn":[0.161967619],"iteration":868,"passed_time":4.112077765,"remaining_time":0.6198874422},
{"learn":[0.1618526814],"iteration":869,"passed_time":4.116400017,"remaining_time":0.6150942555},
{"learn":[0.1617785979],"iteration":870,"passed_time":4.121814884,"remaining_time":0.6104639725},
{"learn":[0.1616988224],"iteration":871,"passed_time":4.125937903,"remaining_time":0.605642261},
{"learn":[0.1616262133],"iteration":872,"passed_time":4.130332288,"remaining_time":0.6008616273},
{"learn":[0.1614856631],"iteration":873,"passed_time":4.135014455,"remaining_time":0.5961233654},
{"learn":[0.1614081183],"iteration":874,"passed_time":4.139704323,"remaining_time":0.5913863318},
{"learn":[0.1613164197],"iteration":875,"passed_time":4.143978005,"remaining_time":0.5865904938},
{"learn":[0.1612199453],"iteration":876,"passed_time":4.148191282,"remaining_time":0.5817873747},
{"learn":[0.1611372736],"iteration":877,"passed_time":4.153214166,"remaining_time":0.5770980959},
{"learn":[0.1610426295],"iteration":878,"passed_time":4.157307043,"remaining_time":0.5722800366},
{"learn":[0.1609823239],"iteration":879,"passed_time":4.161323993,"remaining_time":0.5674532718},
{"learn":[0.1608858856],"iteration":880,"passed_time":4.165688422,"remaining_time":0.5626752807},
{"learn":[0.1608413692],"iteration":881,"passed_time":4.170985355,"remaining_time":0.5580229839},
{"learn":[0.1607429058],"iteration":882,"passed_time":4.175356315,"remaining_time":0.5532465333},
{"learn":[0.1606858026],"iteration":883,"passed_time":4.179707079,"remaining_time":0.5484683497},
{"learn":[0.160581883],"iteration":884,"passed_time":4.184505746,"remaining_time":0.5437493343},
{"learn":[0.1605051051],"iteration":885,"passed_time":4.189069805,"remaining_time":0.5389999524},
{"learn":[0.1604293307],"iteration":886,"passed_time":4.193339406,"remaining_time":0.5342134756},
{"learn":[0.160342568],"iteration":887,"passed_time":4.197472679,"remaining_time":0.5294109685},
{"learn":[0.1602608385],"iteration":888,"passed_time":4.202324088,"remaining_time":0.524699633},
{"learn":[0.160199545],"iteration":889,"passed_time":4.206509029,"remaining_time":0.5199056103},
{"learn":[0.160130238],"iteration":890,"passed_time":4.210697937,"remaining_time":0.5151134401},
{"learn":[0.1600715528],"iteration":891,"passed_time":4.2149482,"remaining_time":0.5103300511},
{"learn":[0.1600110708],"iteration":892,"passed_time":4.220037526,"remaining_time":0.5056483934},
{"learn":[0.1599327676],"iteration":893,"passed_time":4.224680029,"remaining_time":0.5009128446},
{"learn":[0.1598587487],"iteration":894,"passed_time":4.228682193,"remaining_time":0.4961023802},
{"learn":[0.1598077084],"iteration":895,"passed_time":4.233439539,"remaining_time":0.4913813751},
{"learn":[0.1596623386],"iteration":896,"passed_time":4.238150756,"remaining_time":0.486654992},
{"learn":[0.1596196886],"iteration":897,"passed_time":4.242396796,"remaining_time":0.4818758054},
{"learn":[0.159569984],"iteration":898,"passed_time":4.246797887,"remaining_time":0.4771152242},
{"learn":[0.1595250953],"iteration":899,"passed_time":4.251984813,"remaining_time":0.472442757},
{"learn":[0.1594608042],"iteration":900,"passed_time":4.256169051,"remaining_time":0.4676589745},
{"learn":[0.1593324947],"iteration":901,"passed_time":4.260387857,"remaining_time":0.4628802772},
{"learn":[0.1592557287],"iteration":902,"passed_time":4.265332201,"remaining_time":0.4581807569},
{"learn":[0.1591511794],"iteration":903,"passed_time":4.270170805,"remaining_time":0.453469466},
{"learn":[0.1590979262],"iteration":904,"passed_time":4.274368804,"remaining_time":0.4486906479},
{"learn":[0.1589973039],"iteration":905,"passed_time":4.278747714,"remaining_time":0.443931882},
{"learn":[0.1589068884],"iteration":906,"passed_time":4.283946589,"remaining_time":0.4392580296},
{"learn":[0.1588240382],"iteration":907,"passed_time":4.288195674,"remaining_time":0.4344867864},
{"learn":[0.1587481219],"iteration":908,"passed_time":4.292463291,"remaining_time":0.4297185473},
{"learn":[0.1586708454],"iteration":909,"passed_time":4.296912454,"remaining_time":0.4249693636},
{"learn":[0.1586080361],"iteration":910,"passed_time":4.302045601,"remaining_time":0.4202876603},
{"learn":[0.1585427044],"iteration":911,"passed_time":4.306940352,"remaining_time":0.4155819638},
{"learn":[0.1584315833],"iteration":912,"passed_time":4.311470381,"remaining_time":0.4108410987},
{"learn":[0.1583646706],"iteration":913,"passed_time":4.316547559,"remaining_time":0.4061521773},
{"learn":[0.1582657865],"iteration":914,"passed_time":4.321577116,"remaining_time":0.4014579835},
{"learn":[0.1581999303],"iteration":915,"passed_time":4.325945529,"remaining_time":0.3967024284},
{"learn":[0.1580146304],"iteration":916,"passed_time":4.330300554,"remaining_time":0.391946506},
{"learn":[0.1579268804],"iteration":917,"passed_time":4.335284274,"remaining_time":0.3872476149},
{"learn":[0.1578531202],"iteration":918,"passed_time":4.339412593,"remaining_time":0.3824727095},
{"learn":[0.1577918779],"iteration":919,"passed_time":4.343666647,"remaining_time":0.3777101432},
{"learn":[0.15770252],"iteration":920,"passed_time":4.349338289,"remaining_time":0.3730702767},
{"learn":[0.1576240657],"iteration":921,"passed_time":4.353574558,"remaining_time":0.3683067414},
{"learn":[0.157511675],"iteration":922,"passed_time":4.357812831,"remaining_time":0.3635445157},
{"learn":[0.1573914908],"iteration":923,"passed_time":4.361955137,"remaining_time":0.3587755308},
{"learn":[0.1572909804],"iteration":924,"passed_time":4.367560609,"remaining_time":0.3541265358},
{"learn":[0.1571579258],"iteration":925,"passed_time":4.371829518,"remaining_time":0.3493686656},
{"learn":[0.1571089078],"iteration":926,"passed_time":4.376046336,"remaining_time":0.3446077481},
{"learn":[0.1570545395],"iteration":927,"passed_time":4.380767814,"remaining_time":0.339887158},
{"learn":[0.1569918649],"iteration":928,"passed_time":4.385263196,"remaining_time":0.3351492862},
{"learn":[0.1569212242],"iteration":929,"passed_time":4.389434379,"remaining_time":0.3303875339},
{"learn":[0.1568162841],"iteration":930,"passed_time":4.393811144,"remaining_time":0.3256422867},
{"learn":[0.1567280809],"iteration":931,"passed_time":4.399430105,"remaining_time":0.3209884626},
{"learn":[0.1566899538],"iteration":932,"passed_time":4.403554116,"remaining_time":0.3162252152},
{"learn":[0.1566229875],"iteration":933,"passed_time":4.408032613,"remaining_time":0.3114883859},
{"learn":[0.1565756232],"iteration":934,"passed_time":4.412974845,"remaining_time":0.3067843475},
{"learn":[0.1565140065],"iteration":935,"passed_time":4.41745953,"remaining_time":0.3020485149},
{"learn":[0.1564359436],"iteration":936,"passed_time":4.421620129,"remaining_time":0.2972914281},
{"learn":[0.1563758887],"iteration":937,"passed_time":4.425835705,"remaining_time":0.292539247},
{"learn":[0.1563126987],"iteration":938,"passed_time":4.430944943,"remaining_time":0.2878462636},
{"learn":[0.1562283776],"iteration":939,"passed_time":4.435735776,"remaining_time":0.2831320708},
{"learn":[0.1561487932],"iteration":940,"passed_time":4.439838704,"remaining_time":0.278374584},
{"learn":[0.1560873446],"iteration":941,"passed_time":4.443891005,"remaining_time":0.2736153698},
{"learn":[0.1559994358],"iteration":942,"passed_time":4.449341804,"remaining_time":0.2689421875},
{"learn":[0.1559412888],"iteration":943,"passed_time":4.453684721,"remaining_time":0.264201636},
{"learn":[0.1558739475],"iteration":944,"passed_time":4.457997356,"remaining_time":0.2594601636},
{"learn":[0.1558152283],"iteration":945,"passed_time":4.463250264,"remaining_time":0.2547732709},
{"learn":[0.1557319964],"iteration":946,"passed_time":4.467381417,"remaining_time":0.2500224024},
{"learn":[0.155639297],"iteration":947,"passed_time":4.471567308,"remaining_time":0.2452758439},
{"learn":[0.1555878769],"iteration":948,"passed_time":4.47558414,"remaining_time":0.2405213816},
{"learn":[0.1555425857],"iteration":949,"passed_time":4.480879343,"remaining_time":0.2358357549},
{"learn":[0.1554709384],"iteration":950,"passed_time":4.484923736,"remaining_time":0.2310843986},
{"learn":[0.1554077283],"iteration":951,"passed_time":4.489108239,"remaining_time":0.2263415919},
{"learn":[0.1553545042],"iteration":952,"passed_time":4.494308113,"remaining_time":0.2216500329},
{"learn":[0.1552921194],"iteration":953,"passed_time":4.499252565,"remaining_time":0.2169450922},
{"learn":[0.1551851307],"iteration":954,"passed_time":4.503457879,"remaining_time":0.2122048215},
{"learn":[0.1551082491],"iteration":955,"passed_time":4.507816359,"remaining_time":0.2074727194},
{"learn":[0.154998722],"iteration":956,"passed_time":4.513258969,"remaining_time":0.2027901104},
{"learn":[0.1549147933],"iteration":957,"passed_time":4.517402181,"remaining_time":0.1980489474},
{"learn":[0.1548571578],"iteration":958,"passed_time":4.521567386,"remaining_time":0.1933099717},
{"learn":[0.1547996288],"iteration":959,"passed_time":4.52612909,"remaining_time":0.1885887121},
{"learn":[0.1547469139],"iteration":960,"passed_time":4.531284384,"remaining_time":0.1838918741},
{"learn":[0.1546895696],"iteration":961,"passed_time":4.535725044,"remaining_time":0.1791658541},
{"learn":[0.1545744485],"iteration":962,"passed_time":4.539989747,"remaining_time":0.1744336663},
{"learn":[0.1545155796],"iteration":963,"passed_time":4.545216164,"remaining_time":0.169738363},
{"learn":[0.154452091],"iteration":964,"passed_time":4.549477425,"remaining_time":0.1650069532},
{"learn":[0.1543809166],"iteration":965,"passed_time":4.5535774,"remaining_time":0.1602708402},
{"learn":[0.1543119671],"iteration":966,"passed_time":4.557738056,"remaining_time":0.1555381136},
{"learn":[0.15422192],"iteration":967,"passed_time":4.56291408,"remaining_time":0.1508401349},
{"learn":[0.1541729163],"iteration":968,"passed_time":4.566874028,"remaining_time":0.1461022651},
{"learn":[0.1540937104],"iteration":969,"passed_time":4.571022614,"remaining_time":0.1413718334},
{"learn":[0.1539883612],"iteration":970,"passed_time":4.57581846,"remaining_time":0.1366619313},
{"learn":[0.1539425545],"iteration":971,"passed_time":4.580417652,"remaining_time":0.1319461875},
{"learn":[0.1538627927],"iteration":972,"passed_time":4.584793089,"remaining_time":0.1272244742},
{"learn":[0.1537736983],"iteration":973,"passed_time":4.589242625,"remaining_time":0.1225054499},
{"learn":[0.15374195],"iteration":974,"passed_time":4.594296297,"remaining_time":0.1178024692},
{"learn":[0.1536936294],"iteration":975,"passed_time":4.598467892,"remaining_time":0.1130770793},
{"learn":[0.1536194797],"iteration":976,"passed_time":4.602779089,"remaining_time":0.1083561096},
{"learn":[0.1535877809],"iteration":977,"passed_time":4.606888249,"remaining_time":0.103631433},
{"learn":[0.1535150032],"iteration":978,"passed_time":4.612472406,"remaining_time":0.09893965323},
{"learn":[0.1534591082],"iteration":979,"passed_time":4.616661187,"remaining_time":0.09421757524},
{"learn":[0.1533875743],"iteration":980,"passed_time":4.620856615,"remaining_time":0.08949671324},
{"learn":[0.1533360178],"iteration":981,"passed_time":4.626008568,"remaining_time":0.08479445441},
{"learn":[0.153274704],"iteration":982,"passed_time":4.630379124,"remaining_time":0.08007776715},
{"learn":[0.1531942581],"iteration":983,"passed_time":4.634412399,"remaining_time":0.07535629917},
{"learn":[0.1531027757],"iteration":984,"passed_time":4.638588333,"remaining_time":0.070638401},
{"learn":[0.1529947857],"iteration":985,"passed_time":4.643448751,"remaining_time":0.06593132101},
{"learn":[0.1529264196],"iteration":986,"passed_time":4.648598379,"remaining_time":0.06122773953},
{"learn":[0.1528605336],"iteration":987,"passed_time":4.652626054,"remaining_time":0.05650962819},
{"learn":[0.1527954588],"iteration":988,"passed_time":4.656958917,"remaining_time":0.05179630747},
{"learn":[0.1527446564],"iteration":989,"passed_time":4.661775737,"remaining_time":0.04708864381},
{"learn":[0.1526537485],"iteration":990,"passed_time":4.666346043,"remaining_time":0.04237852108},
{"learn":[0.1525725894],"iteration":991,"passed_time":4.670810379,"remaining_time":0.03766782564},
{"learn":[0.1525031834],"iteration":992,"passed_time":4.675863761,"remaining_time":0.03296177878},
{"learn":[0.1524523221],"iteration":993,"passed_time":4.680031816,"remaining_time":0.02824968903},
{"learn":[0.1523809054],"iteration":994,"passed_time":4.684257506,"remaining_time":0.02353898244},
{"learn":[0.1522593597],"iteration":995,"passed_time":4.688498271,"remaining_time":0.01882931033},
{"learn":[0.1520892274],"iteration":996,"passed_time":4.694762712,"remaining_time":0.01412666814},
{"learn":[0.1520084258],"iteration":997,"passed_time":4.69901114,"remaining_time":0.009416855992},
{"learn":[0.1519258545],"iteration":998,"passed_time":4.703261686,"remaining_time":0.004707969655},
{"learn":[0.1518159245],"iteration":999,"passed_time":4.70867995,"remaining_time":0}
]}